{"updated": "2026-07-07T12:00:05+08:00", "source": "竞彩官方API实时赔率(自动抓取 2026-07-07T12:00:05+08:00)", "note": "每小时自动抓取竞彩官方API | SPF更新:0场", "champion_odds": [{"team": "西班牙", "flag": "🇪🇸", "odds": 4.75, "source": "竞彩官方"}, {"team": "法国", "flag": "🇫🇷", "odds": 5, "source": "竞彩官方"}, {"team": "英格兰", "flag": "🏴󠁧󠁢󠁥󠁮󠁧󠁿", "odds": 5, "source": "竞彩官方"}, {"team": "葡萄牙", "flag": "🇵🇹", "odds": 5.75, "source": "竞彩官方"}, {"team": "阿根廷", "flag": "🇦🇷", "odds": 8.5, "source": "竞彩官方"}, {"team": "巴西", "flag": "🇧🇷", "odds": 7, "source": "国际盘口换算"}, {"team": "德国", "flag": "🇩🇪", "odds": 10.5, "source": "竞彩官方"}, {"team": "荷兰", "flag": "🇳🇱", "odds": 15, "source": "国际盘口换算"}], "matches": [{"id": 1, "spf": "待定", "tip": "胜", "level": "🟢铁胆", "totalGoals": "2球/3球", "htft": "胜-胜/平-胜", "score": "2:0/3:0", "code": "周四001", "result": "2:0", "ht_result": "1-0", "postMatch": "【6/12赛果】🇲🇽墨西哥2-0南非:基尼奥内斯9',希门尼斯67';蒙特斯🔴红牌→停赛缺阵下轮vs韩国;揭幕战3红牌创纪录", "injury": "【墨西哥🇲🇽#16】4-3-3;希门尼斯🅕(44球)核心;埃德松🅜中场;奥乔亚🅖6届世界杯;莫拉🅕17岁最年轻;主场阿兹特克9万人+高原2240m;近5场2胜2平1负 | 【南非🇿🇦#74】4-2-3-1;莫科纳🅜核心;福斯特🅕;莫福肯🅕新星;时隔16年回归;H2H:2010世界杯1-1 | 🌍墨西哥城高原主场 | 🔥墨西哥揭幕战压力大", "home": "墨西哥", "away": "南非", "source": "template"}, {"id": 2, "spf": "待定", "tip": "胜", "level": "🟠大概率", "totalGoals": "2球/1球", "htft": "平-胜/胜-胜", "score": "1:0/1:1", "code": "周四002", "result": "2:1", "ht_result": "0-0", "postMatch": "【6/12赛果】🇰🇷韩国2-1逆转捷克:黄仁范67',吴贤揆80'替补绝杀;孙兴慜4射0正但牵制防线;韩国62%控球;出线概率97.7%", "injury": "【韩国🇰🇷#25】4-3-3;孙兴慜🅕(队长)历史射手;李刚仁🅜(PSG);金玟哉🅓核心;16场不败15胜40球;亚洲最强纸面 | 【捷克🇨🇿#35】4-2-3-1;希克🅕前锋;绍切克🅜队长;曹法尔🅓;点球大战晋级;时隔20年回归;H2H:无正式交手 | 🌍瓜达拉哈拉(49K,海拔1566m) | 🔥韩国孙兴慜最后一届", "home": "韩国", "away": "捷克", "source": "ai"}, {"id": 3, "spf": "待定", "tip": "胜", "level": "🟠大概率", "totalGoals": "2球/1球", "htft": "平-胜/胜-胜", "score": "1:0/1:1", "injury": "【加拿大🇨🇦#29】4-4-2;戴维斯🅕❌缺阵首战(腿筋);大卫🅕(法甲射手王);拉林🅕;主场多伦多9万人;求队史世界杯首胜 | 【波黑🇧🇦#56】4-2-3-1;哲科🅕40岁老兵;皮亚尼奇🅜;H2H:首次交手;预选赛淘汰意大利(点球) | 🌍多伦多BMO(30K) | 🔥加拿大主场创历史", "code": "周五003", "result": "1:1", "postMatch": "【6/12赛果】🇨🇦加拿大1-1波黑:卢基奇21'头球,拉林78'扳平;加拿大获队史首个世界杯积分;戴维斯缺阵全场不占优;主场9万人气氛热烈但未转化为胜利", "ht_result": "0:1", "home": "加拿大", "away": "波黑", "source": "ai"}, {"id": 4, "spf": "待定", "tip": "胜", "level": "🟢铁胆", "totalGoals": "2球/3球", "htft": "胜-胜/平-胜", "score": "3:1/2:0", "code": "周五004", "result": "4:1", "postMatch": "【6/12赛果】🇺🇸美国4-1巴拉圭:巴洛贡梅开二度(31'45+5'),雷纳90+8'世界波;普利西奇半场换下⚠️小腿被踢(预防性,需监控);美国创队史世界杯单场进球纪录", "ht_result": "3:0", "injury": "【美国🇺🇸#15】3-4-2-1;普利西奇🅕(AC米兰)核心;巴洛贡🅕(摩纳哥)高效射手;麦肯尼🅜;亚当斯🅜;13人欧洲联赛;东道主主场洛杉矶SoFi | 【巴拉圭🇵🇾#45】4-4-2防守;恩西索🅕⚠️伤前缺阵;阿尔米隆🅕;仅10失球18场南美预选;H2H:美国2胜1平 | 🌍洛杉矶SoFi(70K,主场) | 🔥美国东道主首秀", "home": "美国", "away": "巴拉圭", "source": "ai"}, {"id": 5, "spf": "待定", "tip": "负", "level": "🟢铁胆", "totalGoals": "2球/3球", "htft": "负-负/平-负", "score": "0:2/0:1", "code": "周六005", "result": "1:1", "ht_result": "0:1", "postMatch": "【6/14爆冷】🇶🇦卡塔尔1-1瑞士:卡塔尔首分!阿菲夫点球扳平;瑞士扎卡控场但未能转化优势;卡塔尔门将巴沙姆9次扑救MVP;瑞士出线形势骤紧", "injury": "【卡塔尔🇶🇦#55】4-3-3;阿菲夫🅕亚洲先生;阿里🅕;上届全败0分;实力有限 | 【瑞士🇨🇭#19】4-2-3-1;扎卡🅜队长(勒沃库森核心);恩博洛🅕;阿坎吉🅓;连续3届世界杯出线;H2H:首次交手 | 🌍旧金山Levis(68K) | 🔥瑞士轻松拿捏", "home": "卡塔尔", "away": "瑞士", "source": "template"}, {"id": 6, "spf": "待定", "tip": "胜", "level": "🟠大概率", "totalGoals": "1球/2球", "htft": "平-胜/平-平", "score": "1:0/1:1", "injury": "【巴西】内马尔🅕❌缺阵(小腿拉伤);罗德里戈🅕❌ACL报销;米利唐🅓❌;韦斯利🅓❌;维尼修斯🅕✅+拉菲尼亚🅕✅+恩德里克🅕✅领衔 | 【摩洛哥】阿盖尔德🅓❌+埃扎尔祖利🅕❌;阿什拉夫🅓✅+布努🅖✅+迪亚兹🅜✅核心 | 🌍纽约大都会(82K) | 🔥内马尔看台+安帅战术调整", "code": "周六006", "result": "1:1", "ht_result": "1:1", "postMatch": "【6/14】🇧🇷巴西1-1摩洛哥:内马尔❌看台观战(小腿撕裂);维尼修斯🅕32分世界波扳平;卡塞米罗🅜半场被换(表现差);巴西仅69次进攻三区传球vs摩洛哥123次;布努🅖多次神扑;摩洛哥压制巴西创造历史", "home": "巴西", "away": "摩洛哥", "source": "ai"}, {"id": 7, "spf": "待定", "tip": "负", "level": "🟢铁胆", "totalGoals": "2球/3球", "htft": "负-负/平-负", "score": "0:2/0:3", "code": "周六007", "result": "0:1", "ht_result": "0:1", "postMatch": "【6/14】🇭🇹海地0-1苏格兰:苏格兰控场但效率低;罗伯逊助攻麦金唯一进球;海地首秀虽败犹荣;苏格兰3分到手出线形势好", "injury": "【海地🇭🇹#87】4-4-2;纳宗🅕;伊西多尔🅕;世界杯首秀(48队扩军受益);第二低排名 | 【苏格兰🏴󠁧󠁢󠁳󠁣󠁴󠁿#42】3-4-3;罗伯逊🅓队长;麦金🅜;麦克托米奈🅜;时隔30年重返世界杯;H2H:无交手 | 🌍波士顿吉列(65K) | 🔥苏格兰30年等待", "home": "海地", "away": "苏格兰", "source": "ai"}, {"id": 8, "spf": "待定", "tip": "负", "level": "🔵中等", "totalGoals": "2球/3球", "htft": "平-负/负-负", "score": "0:1/1:2", "code": "周六008", "injury": "【澳大利亚🇦🇺#24】4-3-3;苏塔🅓(1.98m头球);古德温🅕;博伊尔🅕;身体对抗强但技术粗糙 | 【土耳其🇹🇷#33】4-2-3-1;恰尔汗奥卢🅜任意球大师;伊尔迪兹🅕;居莱尔🅜;热身表现波动;H2H:无正式交手 | 🌍温哥华BC Place(55K,室内) | 🔥55开对局", "result": "2:0", "ht_result": "1:0", "postMatch": "【6/14爆冷】🇦🇺澳大利亚2-0土耳其:伊兰昆达27分(最年轻进球者20岁)+梅特卡夫75分;比奇🅖首秀神扑MVP;土耳其28射0中;澳大利亚防守反击教科书", "home": "澳大利亚", "away": "土耳其", "source": "template"}, {"id": 9, "spf": "1.08/9.00/25.00", "tip": "胜", "level": "🟢铁胆", "totalGoals": "5球/4球", "htft": "胜-胜", "score": "4:0/5:0", "injury": "【德国🇩🇪#9】4-2-3-1;诺伊尔🅖✅40岁复出!穆西亚拉🅜✅断腿后恢复首发;维尔茨🅜✅利物浦核心左翼;哈弗茨🅕✅首发中锋;基米希🅜✅右后卫;萨内🅕右翼;格纳布里❌大腿+卡尔❌训练伤退出;H2H:首次交手 | Opta胜率90.7% | 【库拉索🇨🇼#91】世界杯首秀!(人口~20万最小参赛国);L巴库纳🅜队长;钟塔西🅕边锋;洛卡迪亚🅕前锋;阿德沃卡特执教;目标荣誉之战 | 🌍场地:休斯顿NRG(72K人,海拔37m,空调26°C) | 🔥队内:穆西亚拉状态未满但主帅信任;无重大矛盾", "code": "周日009", "result": "7:1", "ht_result": "1:0", "postMatch": "【6/15纪录】德国7-1库拉索:世界杯历史最高得分!穆西亚拉2球+维尔茨2球+哈弗茨1球;德国打破巴西进球纪录", "home": "德国", "away": "库拉索", "source": "template"}, {"id": 10, "spf": "待定", "tip": "平", "level": "🟠大概率", "totalGoals": "1球/2球", "htft": "平-平/胜-平", "score": "1:1/0:0", "injury": "【荷兰】廷贝尔🅓❌(腹股沟);哈维·西蒙斯🅜❌;德利赫特🅓❌;德弗赖🅓❌;斯豪滕🅜❌;范戴克🅓✅+德容🅜✅+加克波🅕✅ | 【日本】三笘薰🅕❌腿筋未入大名单;南野拓实🅜❌ACL;远藤航🅜❌退出退役!久保建英🅜✅+堂安律🅕✅+镰田大地🅜✅支撑 | 🌍达拉斯AT&T(80K,室内25°C) | 🔥日本三核缺阵但残阵斗志强", "code": "周日010", "result": "2:2", "ht_result": "0:0", "postMatch": "【6/15】🇳🇱荷兰2-2日本:范戴克头球+Gakpo进球;日本顽强扳平(久保建英+堂安律);荷兰防线伤潮暴露;日本残阵展现斗志", "home": "荷兰", "away": "日本", "source": "ai"}, {"id": 11, "spf": "待定", "tip": "负", "level": "🔵中等", "totalGoals": "1球/2球", "htft": "平-负/负-负", "score": "0:1/1:1", "code": "周日011", "result": "1:0", "ht_result": "0:0", "postMatch": "【6/15】🇨🇮科特迪瓦1-0厄瓜多尔:阿莱制胜球;厄瓜多尔凯塞多表现平平;科特迪瓦首胜出线希望大增", "injury": "【科特迪瓦🇨🇮#37】4-3-3;阿莱🅕(多特);凯西🅜;佩佩🅕;非洲劲旅 | 【厄瓜多尔🇪🇨#40】4-4-2;凯塞多🅜(切尔西);埃斯图皮尼安🅓;南美预选赛表现好;H2H:首次交手 | 🌍费城林肯金融(67K) | 🔥两队争第二", "home": "科特迪瓦", "away": "厄瓜多尔", "source": "ai"}, {"id": 12, "spf": "待定", "tip": "胜", "level": "🟡稳胆", "totalGoals": "2球/3球", "htft": "胜-胜/平-胜", "score": "2:0/2:1", "code": "周日012", "result": "5:1", "ht_result": "2:1", "postMatch": "【6/15】🇸🇪瑞典5-1突尼斯:伊萨克2球+哲凯赖什2球!瑞典攻击线恐怖;突尼斯防线崩溃;瑞典刷新本届最大比分", "injury": "【瑞典🇸🇪#25】4-4-2;伊萨克🅕(利物浦英超银靴);哲凯赖什🅕(阿森纳);双前锋豪华 | 【突尼斯🇹🇳#50】4-3-3;斯希里🅜;汉尼拔🅜;防守硬朗;H2H:瑞典1胜1平 | 🌍蒙特雷(53K,海拔537m) | 🔥瑞典攻击线恐怖", "home": "瑞典", "away": "突尼斯", "source": "template"}, {"id": 13, "spf": "1.06/10.00/30.00", "tip": "胜", "level": "🟢铁胆", "totalGoals": "2球/3球", "htft": "胜-胜", "score": "2:0/3:0", "injury": "【西班牙🇪🇸#3】4-3-3;亚马尔🅕⚠️腘绳肌手术恢复中(替补15-20分钟);尼科🅕⚠️腿筋不首发;费兰·托雷斯🅕+巴埃纳🅕首发两翼;罗德里🅜+佩德里🅜+法比安🅜三核;费尔明❌退出;近10场不败;H2H:首次交手 | 【佛得角🇨🇻#72】世界杯首秀!(人口<50万最小参赛国之一);门德斯🅜队长;利夫拉门托🅕核心;实力悬殊;目标少丢球 | 🌍场地:亚特兰大梅赛德斯奔驰(71K人,海拔320m,室内25°C);西班牙球迷>70% | 🔥队内:无矛盾,德拉富恩特轮换保护伤员", "code": "周一013", "result": "0:0", "ht_result": "0:0", "postMatch": "【6/15爆冷】西班牙0-0佛得角:世界杯历史最大冷门之一!西班牙75%控球+27次射门0进球;亚马尔+尼科双双替补席出发(伤病管理);佛得角40岁门将沃齐尼亚7次扑救MVP;西班牙攻击力严重受质疑", "home": "西班牙", "away": "佛得角", "source": "ai"}, {"id": 14, "spf": "1.41/3.92/6.05", "tip": "胜", "level": "🟡稳胆", "totalGoals": "1球/2球", "htft": "平-胜/胜-胜", "score": "1:0/2:0", "injury": "【比利时🇧🇪#8】4-3-3;德布劳内🅜✅核心;多库🅕✅边锋;卢卡库🅕⚠️赛季伤病;库尔图瓦🅖✅;特罗萨德🅕✅;近5场3胜1平1负;H2H:首次交手 | 热身5-0突尼斯 | 【埃及🇪🇬#28】萨拉赫🅕✅(本季状态下滑);马尔穆什🅕(曼城新星);防守反击打法;5后卫铁桶阵;预选赛不败 | 🌍场地:西雅图Lumen(69K人,海拔52m,雨18°C) | 🔥队内:比利时黄金一代谢幕战;埃及团结一致 | 🔥比利时黄金一代谢幕", "code": "周一014", "result": "1:1", "ht_result": "0:1", "postMatch": "【6/15】比利时1-1埃及:阿舒尔19破门;卢卡库66替补登场23秒即造乌龙扳平;比利时全场机会浪费严重;德布劳内+多库状态平平;埃及差点历史首胜", "home": "比利时", "away": "埃及", "source": "ai"}, {"id": 15, "spf": "7.50/4.30/1.31", "tip": "负", "level": "🟢铁胆", "totalGoals": "2球/3球", "htft": "负-负/平-负", "score": "0:2/0:1", "code": "周一015", "injury": "【沙特🇸🇦#48】4-3-3;多萨里🅕;谢赫里🅕;上届爆冷胜阿根廷后被高估 | 【乌拉圭🇺🇾#11】3-4-3(贝尔萨疯子战术);努涅斯🅕;巴尔韦德🅜;阿劳霍🅓;H2H:乌拉圭1胜 | 🌍迈阿密硬石(65K,32°C高温) | 🔥贝尔萨高位逼抢", "result": "1:1", "ht_result": "1:0", "home": "沙特阿拉伯", "away": "乌拉圭", "postMatch": "【6/16】沙特1-1乌拉圭:双方各进1球;沙特在美洲拿到宝贵1分;乌拉圭未能展现南美强队风采", "source": "template"}, {"id": 16, "spf": "1.59/3.28/5.10", "tip": "胜", "level": "🟡稳胆", "totalGoals": "1球/2球", "htft": "平-胜/胜-胜", "score": "1:0/2:0", "injury": "【伊朗🇮🇷#18】4-2-3-1;塔雷米🅕核心;贾汉巴赫什🅕;阿兹蒙❌落选;联赛停摆状态存疑 | 【新西兰🇳🇿#82】4-4-2;伍德🅕(诺丁汉)38球队史射手王;仅3次参赛未胜(3平3负);H2H:无交手 | 🌍洛杉矶SoFi(70K) | 🔥伊朗冲击首胜", "code": "周一016", "result": "2:2", "ht_result": "1:1", "home": "伊朗", "away": "新西兰", "postMatch": "【6/16】伊朗2-2新西兰:双方对攻各进2球;新西兰展现顽强战斗力;伊朗未能全取3分", "source": "template"}, {"id": 17, "spf": "1.32/4.20/7.45", "tip": "胜", "level": "🟢铁胆", "totalGoals": "3球/4球", "htft": "胜-胜/平-胜", "score": "2:1/3:1", "injury": "【法国🇫🇷#2】姆巴佩🅕✅状态极佳;登贝莱🅕✅;萨利巴🅓✅;4-2-3-1;德尚最后一届;近5场3胜1平1负(热身1-2负科特迪瓦);H2H塞内加尔:1胜(2002世界杯0-1负) | 【塞内加尔🇸🇳#17】马内🅕✅;库利巴利🅓✅;雅克松🅕;门迪🅖;H2H法国:1胜;非洲冠军挑战世界冠军 | 🌍场地:纽约大都会人寿(82,500人,晴26°C);非洲球迷大批到场 | 🔥队内:姆巴佩vs登贝莱队内地位竞争(金球奖之争);德尚末届后离任", "code": "周二017", "result": "3:1", "ht_result": "0:0", "postMatch": "【6/17赛果】🇫🇷法国3-1塞内加尔:姆巴佩🅕66'82'双响(58球法国历史射手王!)+奥利斯助攻;巴尔科拉82'替补进球;姆巴耶90+5'扳回一城;法国复仇2002;塞内加尔上半场2次中柱", "home": "法国", "away": "塞内加尔", "source": "ai"}, {"id": 18, "spf": "7.00/4.20/1.35", "tip": "负", "level": "🟢铁胆", "totalGoals": "3球/4球", "htft": "负-负/平-负", "score": "0:2/0:3", "code": "周二018", "injury": "【伊拉克🇮🇶#68】4-4-2;无五大联赛球员;亚洲中游 | 【挪威🇳🇴#36】4-3-3;哈兰德🅕(曼城世界第一中锋);厄德高🅜(阿森纳队长);世界杯首秀;H2H:无交手 | 🌍波士顿吉列(65K) | 🔥哈兰德世界杯处子秀", "result": "1:4", "ht_result": "1:2", "postMatch": "【6/17赛果】伊拉克 1-4 挪威:哈兰德双响!厄德高助攻;挪威1998年来首场世界杯胜利", "home": "伊拉克", "away": "挪威", "source": "ai"}, {"id": 19, "spf": "1.29/4.20/8.60", "tip": "胜", "level": "🟡稳胆", "totalGoals": "2球/1球", "htft": "平-胜/胜-胜", "score": "2:0/1:0", "injury": "【阿根廷🇦🇷#1】梅西🅕✅200场里程碑!4-4-2;大马丁🅖✅;塔利亚菲科🅓❌;阿尔瓦雷斯🅕⚠️缺阵;近5场WWWWW(17进1失4零封);H2H:1胜(4-3,2007) | 【阿尔及利亚🇩🇿#43】马赫雷斯🅕✅;本塞拜尼🅓❌脚踝;4场不败(含1-0荷兰);哈吉穆萨🅕+古伊里🅕4球;H2H:1负 | 🌍场地:堪萨斯城Arrowhead体育场(76,416人,海拔277m);天气:晴28°C;满座;阿根廷球迷占比>60% | 🔥队内:无矛盾,斯卡洛尼团队凝聚力高;阿尔及利亚团结一致挑战冠军", "code": "周二019", "result": "3:0", "ht_result": "1:0", "postMatch": "【6/17赛果】🇦🇷阿根廷3-0阿尔及利亚:梅西🅕帽子戏法!!!17'+下半场+76';世界杯16球追平克洛泽纪录;第6届世界杯首帽;38岁传奇;南美首胜", "home": "阿根廷", "away": "阿尔及利亚", "source": "ai"}, {"id": 20, "spf": "1.25/4.75/8.40", "tip": "胜", "level": "🟢铁胆", "totalGoals": "2球/3球", "htft": "胜-胜", "score": "2:0/3:0", "code": "周二020", "injury": "【奥地利🇦🇹#21】4-2-3-1(朗尼克高位逼抢);阿拉巴🅓;萨比策🅜;莱默尔🅜;鲍姆加特纳❌退出 | 【约旦🇯🇴#64】4-4-2;亚洲中下游;H2H:无交手 | 首战3-1约旦(施密德+阿瑙) | 🌍旧金山Levis(68K) | 🔥朗尼克体系首秀", "result": "3:1", "ht_result": "1:0", "postMatch": "【6/17】奥地利3-1约旦:施密德21分远射;约旦50分扳平;77分乌龙+90+12阿瑙托维奇点球;奥地利36年来世界杯首胜", "home": "奥地利", "away": "约旦", "source": "template"}, {"id": 21, "spf": "1.13/5.86/13.50", "tip": "胜", "level": "🟢铁胆", "totalGoals": "2球/3球", "htft": "胜-胜", "score": "3:0/2:0", "injury": "【葡萄牙]✅全员健康🇵🇹#5】4-3-3;C罗🅕最后一届!B费🅜核心;B席🅜;莱奥🅕;迪亚斯🅓;全员健康! | 【民主刚果🇨🇩#61】4-4-2;非洲中游;世界杯罕见面孔;H2H:首次交手 | 首战1-1民主刚果(若昂内维斯破门) | 🌍休斯顿NRG(72K) | 🔥C罗谢幕演出首战", "code": "周三021", "postMatch": "【6/17爆冷】葡萄牙1-1民主刚果:若昂内维斯6分破门;维萨45+5扳平;C罗错失2次良机+大赛10场球荒;葡萄牙射正仅1次;民主刚果52年来首个世界杯积分!历史性平局", "home": "葡萄牙", "away": "民主刚果", "result": "1:1", "ht_result": "1:1", "source": "ai"}, {"id": 22, "spf": "1.52/3.55/5.27", "tip": "胜", "level": "🟡稳胆", "totalGoals": "2球/1球", "htft": "胜-胜/平-胜", "score": "2:1/1:0", "injury": "【英格兰🏴󠁧󠁢󠁥󠁮󠁧󠁿#4】4-2-3-1;凯恩🅕✅;贝林厄姆🅜✅10号位;萨卡🅕⚠️小腿;斯通斯🅓+孔萨🅓首发;H2H克罗地亚:5胜2平3负(2018世界杯半决赛1-2负) | 【克罗地亚🇭🇷#10】莫德里奇🅜✅最后一届;格瓦迪奥尔🅓✅;科瓦契奇🅜✅;H2H英格兰:3胜2平5负 | 近5场2W1D1L(1-0新西兰,负日本) | 🌍场地:达拉斯AT&T体育场(80,000人,室内空调25°C);英格兰球迷35,000+;中立场地 | 🔥队内:萨卡vs马杜埃克首发之争;图赫尔确认贝林10号位;无重大矛盾", "code": "周三022", "result": "4:2", "ht_result": "2:2", "home": "英格兰", "away": "克罗地亚", "postMatch": "【6/18】英格兰4-2克罗地亚:凯恩双响(9分点球+42分头球);巴图里纳36分扳平;下半场英格兰2球锁定;贝林厄姆2助攻MVP", "source": "ai"}, {"id": 23, "spf": "2.04/3.03/3.23", "tip": "胜", "level": "🟡稳胆", "totalGoals": "2球/1球", "htft": "胜-胜/平-胜", "score": "1:0/2:0", "code": "周三023", "injury": "【加纳]⚠️托马斯存疑🇬🇭#60】4-3-3;库杜斯🅕(西汉姆);托马斯🅜(阿森纳);非洲劲旅身体对抗强 | 【巴拿马🇵🇦#54】4-4-2;2018年首秀三战全败;H2H:无交手 | 近5场2W1D2L | 🌍多伦多BMO(30K) | 🔥加纳争出线关键战", "result": "1:0", "ht_result": "0:0", "home": "加纳", "away": "巴拿马", "postMatch": "【6/18】加纳1-0巴拿马:加纳首胜;巴拿马世界杯第二场失利", "source": "template"}, {"id": 24, "spf": "9.65/4.85/1.22", "tip": "负", "level": "🟢铁胆", "totalGoals": "2球/3球", "htft": "负-负/平-负", "score": "0:2/0:1", "code": "周三024", "injury": "【乌兹别克斯坦]✅J罗+迪亚斯🇺🇿#58】4-4-2;亚洲中游;世界杯首秀(扩军受益) | 【哥伦比亚🇨🇴#12】4-3-3;迪亚斯🅕(利物浦);J罗🅜核心;南美劲旅;H2H:无交手 | 近5场1W2D2L | 🌍墨西哥城阿兹特克(87K,2240m) | 🔥哥伦比亚J罗最后一届", "result": "1:3", "ht_result": "0:1", "home": "乌兹别克斯坦", "away": "哥伦比亚", "postMatch": "【6/18】乌兹别克1-3哥伦比亚:哥伦比亚J罗+迪亚斯建功;乌兹别克世界杯首分", "source": "template"}, {"id": 25, "spf": "1.61/3.50/4.50", "tip": "胜", "level": "🟡稳胆", "totalGoals": "2球/1球", "htft": "胜-胜/平-胜", "score": "2:0/1:0", "injury": "【捷克🇨🇿#35】4-2-3-1;绍切克🅜(西汉姆,队长);希克🅕;克雷伊奇🅓;首战1-2负韩国 | 【南非🇿🇦#56】4-3-3;首战0-2负墨西哥;2红牌停赛 | 🌍亚特兰大梅赛德斯(71K) | 🔥捷克争出线 | 近5场2W2D1L | H2H:首次交手", "code": "周四025", "home": "捷克", "away": "南非", "result": "1:1", "ht_result": "1:0", "postMatch": "【6/19】捷克1-1南非:萨迪莱克5分闪电破门;南非顽强扳平;双方各取1分A组垫底", "source": "ai"}, {"id": 26, "spf": "1.38/3.95/6.60", "tip": "胜", "level": "🟢铁胆", "totalGoals": "2球/1球", "htft": "胜-胜/平-胜", "score": "2:0/1:0", "injury": "【瑞士🇨🇭#19】4-2-3-1;扎卡🅜队长;恩博洛🅕;阿坎吉🅓;首战1-1平卡塔尔爆冷 | 【波黑🇧🇦#56】4-4-2;哲科🅕40岁;首轮未赛;H2H:无交手 | 🌍洛杉矶SoFi(70K) | 🔥瑞士急需3分", "code": "周四026", "home": "瑞士", "away": "波黑", "result": "4:1", "ht_result": "1:0", "postMatch": "【6/19】瑞士4-1波黑:曼赞比替补双响;瓦尔加斯+扎卡各1球;瑞士首胜出线在望", "source": "ai"}, {"id": 27, "spf": "1.17/5.45/11.00", "tip": "胜", "level": "🟢铁胆", "totalGoals": "2球/3球", "htft": "胜-胜/平-胜", "score": "2:0/2:1", "injury": "【加拿大🇨🇦#29】4-4-2;戴维斯🅕✅回归;大卫🅕;拉林🅕;首战1-1平波黑 | 【卡塔尔🇶🇦#55】4-3-3;阿菲夫🅕;首战1-1平瑞士创造历史!巴沙姆🅖9次扑救MVP | 🌍温哥华BC(55K,主场) | 🔥加拿大求历史首胜", "code": "周四027", "home": "加拿大", "away": "卡塔尔", "result": "6:0", "ht_result": "3:0", "postMatch": "【6/19】加拿大6-0卡塔尔:乔纳森戴维帽子戏法!加拿大历史首胜!2红牌;卡塔尔溃败", "source": "ai"}, {"id": 28, "spf": "1.91/2.86/3.90", "tip": "胜", "level": "🟠大概率", "totalGoals": "2球/3球", "htft": "胜-胜/平-胜", "score": "2:0/1:0", "injury": "【墨西哥】蒙特斯🅓🔴红牌停赛(下轮vs韩国缺阵);揭幕战2-0统治南非但消耗大 | 【韩国】2-1逆转捷克士气大振;孙兴慜4射0正但牵制力强;黄仁范+吴贤揆进球;62%控球率;出线概率97.7%", "code": "周四028", "home": "墨西哥", "away": "韩国", "result": "1:0", "ht_result": "1:0", "postMatch": "【6/19】墨西哥1-0韩国:墨西哥6分首个晋级16强!韩国3分A组第二", "source": "ai"}, {"id": 29, "spf": "1.45/3.83/5.60", "tip": "胜", "level": "🟢铁胆", "totalGoals": "2球/4球", "htft": "胜-胜/平-胜", "score": "2:0/3:1", "injury": "【美国】首战4-1巴拉圭创队史纪录;巴洛贡🅕🔥2球状态火热;普利西奇🅕⚠️半场被换(小腿预防性,出战存疑);雷纳🅜世界波 | 【澳大利亚】首轮未赛(6/14vs土耳其)", "code": "周五029", "home": "美国", "away": "澳大利亚", "result": "2:0", "ht_result": "1:0", "postMatch": "【6/20】美国2-0澳大利亚:普利西奇缺阵仍轻松取胜;美国6分提前晋级;澳洲3分", "source": "ai"}, {"id": 30, "spf": "5.10/3.28/1.59", "tip": "负", "level": "🔵中等", "totalGoals": "1球/2球", "htft": "负-负/平-负", "score": "0:1/0:2", "injury": "【摩洛哥】首战1-1逼平巴西!表现超预期:压制巴西(123次三区传球vs69);布努🅖神勇;迪亚兹🅜+萨伊巴里🅜进球组织;2022四强实力再现 | 【苏格兰】首战1-0小胜海地;罗伯逊🅓+麦金🅜状态好", "code": "周五030", "home": "苏格兰", "away": "摩洛哥", "result": "0:1", "ht_result": "0:0", "postMatch": "【6/20】苏格兰0-1摩洛哥:赛巴里71秒闪电破门(非洲最快);摩洛哥4分;苏格兰3分", "source": "ai"}, {"id": 31, "spf": "1.06/10.00/30.00", "tip": "胜", "level": "🟢铁胆", "totalGoals": "4球/5球", "htft": "胜-胜", "score": "2:0/3:0", "injury": "【巴西】首战1-1平摩洛哥暴露问题:内马尔🅕❌看台;进攻组织混乱(仅69次三区传球);卡塞米罗🅜半场被换;维尼修斯🅕状态好(1球);安帅需调整中场 | 【海地】首秀0-1苏格兰表现顽强;实力有限", "code": "周五031", "home": "巴西", "away": "海地", "result": "3:0", "ht_result": "2:0", "postMatch": "【6/20】巴西3-0海地:库尼亚双响+内马尔替补;巴西4分提前晋级;海地0分出局", "source": "ai"}, {"id": 32, "spf": "1.92/3.10/3.50", "tip": "胜", "level": "🟡稳胆", "totalGoals": "2球/3球", "htft": "胜-胜/平-胜", "score": "1:0/2:0", "injury": "【土耳其🇹🇷#33】4-2-3-1;恰尔汗奥卢🅜;伊尔迪兹🅕;居莱尔🅜;首轮未赛 | 【巴拉圭🇵🇾#45】4-4-2;阿尔米隆🅕;恩西索🅕⚠️;H2H:无交手 | 🌍旧金山Levis(68K) | 🔥两队争第二", "code": "周五032", "home": "土耳其", "away": "巴拉圭", "result": "0:1", "ht_result": "0:0", "postMatch": "【6/20】土耳其0-1巴拉圭:巴拉圭获首胜;土耳其2连败;D组形势混乱", "source": "template"}, {"id": 33, "spf": "1.59/3.58/4.52", "tip": "胜", "level": "🔵中等", "totalGoals": "2球/3球", "htft": "平-胜/胜-胜", "score": "2:1/1:1", "injury": "【荷兰】首战2-2平日本暴露防线伤潮;廷贝尔🅓❌+德利赫特🅓❌严重影响;范戴克🅓✅进球但防守漏洞多 | 【瑞典】首战5-1屠突尼斯!伊萨克🅕2球+哲凯赖什🅕2球超级火力;攻击线状态恐怖", "code": "周六033", "home": "荷兰", "away": "瑞典", "result": "5:1", "ht_result": "3:1", "postMatch": "【6/21】荷兰5-1瑞典:荷兰火力全开破纪录;瑞典防线崩溃;荷兰4分", "source": "ai"}, {"id": 34, "spf": "1.40/4.15/5.75", "tip": "胜", "level": "🟢铁胆", "totalGoals": "3球/2球", "htft": "胜-胜/平-胜", "score": "3:0/2:0", "injury": "【德国🇩🇪#9】4-2-3-1;穆西亚拉🅜;维尔茨🅜(利物浦);哈弗茨🅕;首战碾压库拉索 | 【科特迪瓦🇨🇮#37】4-3-3;阿莱🅕;凯西🅜;首战1-0胜厄瓜多尔状态好 | 🌍多伦多BMO(30K) | 🔥德国vs非洲冠军", "code": "周六034", "home": "德国", "away": "科特迪瓦", "result": "2:1", "ht_result": "0:1", "postMatch": "【6/21】德国2-1科特迪瓦:德国逆转取胜6分晋级;辛戈重伤退赛科特迪瓦3分", "source": "template"}, {"id": 35, "spf": "1.30/5.00/9.00", "tip": "胜", "level": "🟢铁胆", "totalGoals": "3球/2球", "htft": "胜-胜", "score": "3:0/2:0", "injury": "【厄瓜多尔🇪🇨#40】4-4-2;凯塞多🅜;埃斯图皮尼安🅓;首战0-1负科特迪瓦 | 【库拉索🇨🇼#91】4-4-2;L巴库纳🅜;世界杯首秀;实力悬殊 | 🌍堪萨斯城Arrowhead(76K) | 🔥厄瓜多尔必须赢", "code": "周六035", "home": "厄瓜多尔", "away": "库拉索", "result": "0:0", "ht_result": "0:0", "postMatch": "【6/21】厄瓜多尔0-0库拉索:闷平;厄瓜多尔本届2战仅1球;库拉索首分", "source": "ai"}, {"id": 36, "spf": "5.75/3.70/1.46", "tip": "负", "level": "🟠大概率", "totalGoals": "2球/3球", "htft": "负-负/平-负", "score": "0:2/0:1", "injury": "【日本】三笘薰❌+南野拓实❌+远藤航❌退出(三大核心全缺);久保建英+堂安律支撑 | 【瑞典】伊萨克+哲凯赖什双前锋豪华;实力碾压残阵日本", "code": "周六036", "home": "突尼斯", "away": "日本", "result": "0:4", "ht_result": "0:2", "postMatch": "【6/21】突尼斯0-4日本:日本残阵大胜!久保建英+堂安律各1球;日本3分", "source": "ai"}, {"id": 37, "spf": "1.12/8.00/18.00", "tip": "胜", "level": "🟢铁胆", "totalGoals": "4球/5球", "htft": "胜-胜", "score": "4:0/5:0", "injury": "【西班牙🇪🇸#3】4-3-3;罗德里🅜金球级;佩德里🅜+加维🅜双核;亚马尔🅕⚠️替补;C罗式碾压 | 【沙特🇸🇦#48】4-3-3;多萨里🅕;上届爆冷胜阿根廷后被高估;H2H:西班牙1胜 | 🌍亚特兰大(71K) | 🔥西班牙轮换为主", "code": "周日037", "home": "西班牙", "away": "沙特阿拉伯", "result": "4:0", "ht_result": "2:0", "postMatch": "【6/22】西班牙4-0沙特阿拉伯:亚马尔首球+费兰双响;西班牙首胜;沙特1分", "source": "ai"}, {"id": 38, "spf": "1.55/3.80/6.00", "tip": "胜", "level": "🟢铁胆", "totalGoals": "2球/3球", "htft": "胜-胜/平-胜", "score": "2:0/2:1", "injury": "【比利时🇧🇪#8】4-3-3;德布劳内🅜;多库🅕;卢卡库🅕⚠️;首战1-0埃及;库尔图瓦🅖神勇 | 【伊朗🇮🇷#18】4-2-3-1;塔雷米🅕;首轮未赛;联赛停摆状态存疑 | 🌍洛杉矶SoFi(70K) | 🔥比利时头名战", "code": "周日038", "home": "比利时", "away": "伊朗", "result": "0:0", "ht_result": "0:0", "postMatch": "【6/22】比利时0-0伊朗:德布劳内全场最佳但无法破门;伊朗铁桶阵;比利时2分", "source": "ai"}, {"id": 39, "spf": "1.25/5.50/10.00", "tip": "胜", "level": "🟢铁胆", "totalGoals": "3球/2球", "htft": "胜-胜", "score": "3:0/2:0", "injury": "【乌拉圭🇺🇾#11】3-4-3贝尔萨;努涅斯🅕;巴尔韦德🅜;阿劳霍🅓;首战1-1沙特(爆冷平局) | 【佛得角🇨🇻#72】4-4-2;门德斯🅜;世界杯首秀;首战0-0平西班牙(超级爆冷) | 🌍迈阿密硬石(65K) | 🔥乌拉圭捞净胜球", "code": "周日039", "home": "乌拉圭", "away": "佛得角", "result": "2:2", "ht_result": "1:1", "postMatch": "【6/22】乌拉圭2-2佛得角:皮纳30米任意球破门;乌拉圭连追2球;H组大混战", "source": "template"}, {"id": 40, "spf": "3.80/3.20/2.10", "tip": "负", "level": "🟡稳胆", "totalGoals": "2球/1球", "htft": "负-负/平-负", "score": "0:1/1:2", "injury": "【新西兰🇳🇿#82】4-4-2;伍德🅕38球;仅3次参赛0胜 | 【埃及🇪🇬#28】4-2-3-1防反;萨拉赫🅕⚠️下滑;马尔穆什🅕;5后卫铁桶 | 🌍温哥华BC(55K) | 🔥埃及出线关键战", "code": "周日040", "home": "新西兰", "away": "埃及", "result": "2:2", "postMatch": "【6/22】新西兰2-2埃及:萨拉赫双响;新西兰顽强扳平;各取1分", "source": "ai"}, {"id": 41, "spf": "1.31/4.20/7.85", "tip": "胜", "level": "🟡稳胆", "totalGoals": "2球/1球", "htft": "胜-胜/平-胜", "score": "2:1/1:0", "injury": "【阿根廷🇦🇷#1】4-4-2;梅西🅕✅200场首秀帽子戏法!;大马丁🅖✅;阿尔瓦雷斯🅕✅复出;莫利纳🅓✅恢复;塔利亚菲科🅓❌;首战3-0阿尔及利亚(梅西3球) | 【奥地利🇦🇹#21】4-2-3-1朗尼克高位;阿拉巴🅓✅;萨比策🅜✅;阿瑙托维奇🅕✅(首战补时点球);鲍姆加特纳❌退出;首战3-1约旦(艰难) | 🌍达拉斯AT&T(80K,室内25°C) | H2H:3次交手(阿根廷1胜1平1负) | 🔥梅西冲击世界杯17球新纪录", "code": "周一041", "home": "阿根廷", "away": "奥地利", "result": "2:0", "source": "ai", "postMatch": "阿根廷 2:0 奥地利 | 梅西2球(38'/90+5')破克洛泽世界杯纪录(18球),9'罚丢点球;阿根廷全场控球率62%,两连胜锁定小组头名晋级32强"}, {"id": 42, "spf": "1.08/9.00/25.00", "tip": "胜", "level": "🟢铁胆", "totalGoals": "4球/5球", "htft": "胜-胜", "score": "4:0/3:0", "injury": "【法国🇫🇷#2】4-2-3-1;姆巴佩🅕✅(首战双响58球射手王);登贝莱🅕✅;萨利巴🅓✅;特奥🅓✅;首战3-1塞内加尔 | 【伊拉克🇮🇶#68】4-4-2;侯赛因🅕(预选赛射手);首战1-4负挪威;实力差距明显 | 🌍费城林肯(67K) | H2H:首次交手 | 🔥姆巴佩冲击60球+德尚末届", "code": "周一042", "home": "法国", "away": "伊拉克", "result": "3:0", "source": "ai", "postMatch": "法国 3:0 伊拉克 | 姆巴佩2球(14'/54')追平克洛泽16球,登贝莱66'破门;比赛因雷雨中断2小时;法国两连胜提前出线"}, {"id": 43, "spf": "1.97/3.23/3.20", "tip": "胜", "level": "🔵中等", "totalGoals": "2球/3球", "htft": "胜-胜/平-胜", "score": "2:0/1:0", "injury": "【挪威🇳🇴#36】4-3-3;哈兰德🅕✅(首战2球世界杯处子秀);厄德高🅜✅(队长);瑟洛特🅕;首战4-1伊拉克(碾压) | 【塞内加尔🇸🇳#17】4-3-3;马内🅕✅;雅克松🅕;库利巴利🅓⚠️(腿筋,首战仅8分钟);首战1-3负法国(上半场2中柱) | 🌍纽约大都会(82K) | H2H:首次交手 | 🔥哈兰德vs非洲冠军", "code": "周一043", "home": "挪威", "away": "塞内加尔", "result": "3:2", "source": "ai", "postMatch": "挪威 3:2 塞内加尔 | 哈兰德2球(48'/58')4场4球,佩德森43'首开纪录;萨尔2球(53'/90+3')难救主;挪威两连胜晋级32强"}, {"id": 44, "spf": "6.50/4.36/1.34", "tip": "负", "level": "🟡稳胆", "totalGoals": "2球/1球", "htft": "负-负/平-负", "score": "0:2/0:1", "injury": "【约旦🇯🇴#64】4-4-2;塔马里🅕(蒙彼利埃);首战1-3负奥地利(一度扳平,乌龙+补时点球);亚洲中下游 | 【阿尔及利亚🇩🇿#43】4-3-3;马赫雷斯🅕✅(队长);本塞拜尼🅓❌脚踝;古伊里🅕;首战0-3负阿根廷(梅西帽子戏法) | 🌍旧金山Levis(68K) | H2H:首次交手 | 🔥阿尔及利亚必须赢", "code": "周一044", "home": "约旦", "away": "阿尔及利亚", "result": "1:2", "ht_result": "1:0", "source": "ai", "postMatch": "约旦 1:2 阿尔及利亚 | 约旦36'拉什丹破门领先;阿尔及利亚69'本布阿利角球头球扳平,82'古伊里补射绝杀;约旦两连败出局"}, {"id": 45, "spf": "1.18/6.50/15.00", "tip": "胜", "level": "🟢铁胆", "totalGoals": "2球/3球", "htft": "胜-胜", "score": "2:0/3:0", "injury": "【葡萄牙🇵🇹#5】4-3-3;C罗🅕✅(首战76分钟无进球10场球荒);B费🅜✅;莱奥🅕✅;若昂内维斯🅜✅(首战进球);全员健康;首战1-1爆冷平民主刚果(射正仅1次) | 【乌兹别克斯坦🇺🇿#58】4-4-2;肖穆罗多夫🅕;首战1-3负哥伦比亚;亚洲中游 | 🌍休斯顿NRG(72K) | H2H:首次交手 | 🔥C罗求破球荒", "code": "周二045", "home": "葡萄牙", "away": "乌兹别克斯坦", "result": "5:0", "ht_result": "3:0", "source": "ai", "postMatch": "葡萄牙 5:0 乌兹别克斯坦 | C罗2球(6'/39')成史上首位6届世界杯进球者,10球超尤西比奥成葡萄牙世界杯射手王;门德斯17'任意球破门,莱奥87'锦上添花;葡萄牙5-0大胜"}, {"id": 46, "spf": "1.35/4.50/8.00", "tip": "胜", "level": "🟢铁胆", "totalGoals": "2球/3球", "htft": "胜-胜/平-胜", "score": "2:0/3:0", "injury": "【英格兰🏴󠁧󠁢󠁥󠁮󠁧󠁿#4】4-2-3-1;凯恩🅕✅(首战2球);贝林厄姆🅜✅(首战2助攻MVP);萨卡🅕⚠️(跟腱炎,可能替补);斯通斯🅓✅;首战4-2克罗地亚 | 【加纳🇬🇭#60】4-3-3;库杜斯🅕✅(西汉姆);托马斯🅜⚠️存疑;首战1-0巴拿马 | 🌍波士顿吉列(65K) | H2H:首次正式交手 | 🔥英格兰冲连胜提前出线", "code": "周二046", "home": "英格兰", "away": "加纳", "result": "0:0", "ht_result": "0:0", "source": "ai", "postMatch": "英格兰 0:0 加纳 | 英格兰78%控球19射仅3正;凯恩87'门前6码打飞;加纳79'禁区犯规裁判未判点球引争议;英格兰连续4届大赛次轮平局"}, {"id": 47, "spf": "6.90/4.30/1.33", "tip": "负", "level": "🟢铁胆", "totalGoals": "2球/3球", "htft": "负-负/平-负", "score": "0:2/0:1", "injury": "【巴拿马🇵🇦#54】4-4-2;2018首秀3战全败;首战0-1负加纳;实力有限 | 【克罗地亚🇭🇷#10】4-3-3;莫德里奇🅜✅(40岁最后一届);格瓦迪奥尔🅓✅;科瓦契奇🅜✅;首战2-4负英格兰(顽强) | 🌍多伦多BMO(30K) | H2H:首次交手 | 🔥魔笛告别演出", "code": "周二047", "home": "巴拿马", "away": "克罗地亚", "result": "0:1", "ht_result": "0:0", "source": "ai", "postMatch": "巴拿马 0:1 克罗地亚 | 莫德里奇第200场国家队出场(史上第4人);布迪米尔54'替补9分钟破门绝杀;利瓦科维奇多次神扑保住胜局;巴拿马两连败出局"}, {"id": 48, "spf": "1.50/3.80/6.50", "tip": "胜", "level": "🟢铁胆", "totalGoals": "2球/1球", "htft": "胜-胜/平-胜", "score": "2:0/1:0", "injury": "【哥伦比亚🇨🇴#12】4-3-3;迪亚斯🅕✅(利物浦);J罗🅜✅;首战3-1乌兹别克斯坦 | 【民主刚果🇨🇩#61】4-4-2;巴坎布🅕;维萨🅕(首战进球扳平葡萄牙);万-比萨卡🅓;首战1-1爆冷平葡萄牙(52年首分) | 🌍墨西哥城阿兹特克(87K,2240m) | H2H:首次交手 | 🔥刚果再爆冷?", "home": "哥伦比亚", "away": "民主刚果", "result": "1:0", "ht_result": "0:0", "source": "template", "postMatch": "哥伦比亚 1:0 民主刚果 | 穆尼奥斯76'制胜球(连续两场破门);MPAsi门将上半场5次扑救创纪录;路易斯迪亚斯两球被吹;哥伦比亚两连胜头名出线"}, {"id": 49, "spf": "待定", "tip": "胜", "level": "🟠大概率", "totalGoals": "2球/1球", "htft": "胜-胜/平-胜", "score": "2:0/1:0", "note": "瑞士vs加拿大-B组出线决战", "injury": "【瑞士#19】4-3-3;扎卡🅜✅队长;恩博洛🅕✅;曼赞比🅕🔥(超级替补2球);阿坎吉🅓✅;上轮4-1波黑 | 【加拿大#29】4-4-2;戴维斯🅕✅复出;科内🅜❌断腿报销;大卫🅕✅(帽子戏法);拉林🅕✅;上轮6-0卡塔尔 | 🌍温哥华BC(55K,主场) | 🔥B组头名之争 | H2H:首次交手", "home": "瑞士", "away": "加拿大", "result": "2:1", "ht_result": "1:1", "postMatch": "【6/25】瑞士2-1加拿大:恩博洛55分破门;曼赞比替补78分绝杀;戴维斯复出但无力回天;瑞士7分B组头名;加拿大4分仍晋级", "source": "ai"}, {"id": 50, "spf": "待定", "tip": "负", "level": "🔵中等", "injury": "【波黑#56】4-4-2;哲科🅕✅(2球);德米罗维奇🅕✅;穆哈雷莫维奇🅓❌红牌停赛;上轮1-4瑞士 | 【卡塔尔#55】4-3-3;阿菲夫🅕✅;2人红牌停赛;上轮0-6加拿大 | 🌍西雅图Lumen(69K) | 🔥必须赢否则淘汰 | H2H:首次交手", "home": "波黑", "away": "卡塔尔", "score": "0:1/0:2", "htft": "负-负/平-负", "totalGoals": "2球/1球", "result": "3:1", "ht_result": "2:0", "postMatch": "【6/25】波黑3-1卡塔尔:哲科2球!;卡塔尔10人应战;波黑4分有望最佳第三;卡塔尔1分出局", "source": "ai"}, {"id": 51, "spf": "待定", "tip": "负", "level": "🟢铁胆", "totalGoals": "3球/4球", "htft": "负-负", "score": "0:3/0:4", "note": "巴西大概率大胜苏格兰", "injury": "【苏格兰#42】4-4-1-1;罗伯逊🅓✅;麦金🅜✅;蒂尔尼🅓✅伤愈;上轮0-1摩洛哥 | 【巴西#6】4-2-3-1;内马尔🅕✅复出(981天首秀);拉菲尼亚🅕❌腘绳肌;库尼亚🅕🔥(2球);维尼修斯🅕✅;上轮3-0海地 | 🌍迈阿密硬石(65K) | 🔥内马尔回归 | H2H:巴西8场不败", "home": "苏格兰", "away": "巴西", "result": "0:3", "ht_result": "0:2", "postMatch": "【6/25】苏格兰 0-3 巴西:内马尔替补30分钟1助攻!;库尼亚+维尼修斯+拉扬各1球;巴西7分C组头名;苏格兰3分等最佳第三", "source": "ai"}, {"id": 52, "spf": "待定", "tip": "胜", "level": "🟡稳胆", "totalGoals": "2球/3球", "htft": "胜-胜/平-胜", "score": "2:0/1:0", "note": "摩洛哥vs海地", "injury": "【摩洛哥#13】4-2-3-1;阿什拉夫🅓✅;布努🅖✅;迪亚兹🅜✅;赛巴里🅕🔥(2球);31场不败!上轮1-0苏格兰 | 【海地#87】已提前出局;上轮0-3巴西 | 🌍亚特兰大(71K) | 🔥摩洛哥刷净胜球争头名 | H2H:首次交手", "home": "摩洛哥", "away": "海地", "result": "4:2", "ht_result": "2:0", "postMatch": "【6/25】摩洛哥4-2海地:赛巴里+迪亚兹双响;海地获世界杯首球;摩洛哥7分小组第二;海地0分出局", "source": "ai"}, {"id": 53, "spf": "待定", "tip": "负", "level": "🟡稳胆", "note": "捷克vs墨西哥-A组出线决战【06-13】🇲🇽墨西哥:蒙特斯红牌停赛缺阵(防线关键缺失)", "injury": "【捷克#35】3-5-2;绍切克🅜✅队长;希克🅕✅;尤拉塞克❌退赛;上轮1-1南非;必须赢+等韩国输 | 【墨西哥#16】4-2-3-1;大幅轮换!奥乔亚🅖(6届世界杯);蒙特斯🅓✅红牌解禁;已头名出线;上轮1-1韩国 | 🌍阿兹特克(87K,2240m) | 🔥墨西哥放水+捷克拼死 | H2H:首次交手", "home": "捷克", "away": "墨西哥", "score": "0:1/0:2", "htft": "负-负/平-负", "totalGoals": "2球/1球", "result": "0:0", "ht_result": "0:0", "postMatch": "【6/25】捷克0-0墨西哥:墨西哥大幅轮换;捷克狂攻无果;双方各取1分;捷克2分等最佳第三", "source": "ai"}, {"id": 54, "spf": "待定", "tip": "负", "level": "🟢铁胆", "note": "南非vs韩国", "injury": "【南非#56】4-3-3;莫科纳🅜❌黄牌停赛;兹瓦内❌停赛;西索尔✅红牌解禁;上轮1-1捷克;必须赢球 | 【韩国#23】3-4-2-1;孙兴慜🅕✅(前2场0球);李刚仁🅜✅;不败即出线 | 🌍蒙特雷(53K,>35°C) | 🔥生死战 | H2H:首次交手", "home": "南非", "away": "韩国", "score": "0:1/0:2", "htft": "负-负/平-负", "totalGoals": "2球/1球", "result": "0:0", "ht_result": "0:0", "postMatch": "【6/25】南非0-0韩国:高温35°C闷平;孙兴慜全场0射门;韩国4分小组第二出线!;南非2分出局", "source": "ai"}, {"id": 55, "spf": "待定", "tip": "负", "level": "🟢铁胆", "totalGoals": "3球/4球", "htft": "负-负/平-负", "score": "0:3/1:3", "note": "德国vs厄瓜多尔", "injury": "【厄瓜多尔#40】4-4-2;凯塞多🅜✅(切尔西);埃斯图皮尼安🅓✅;2战仅1球;必须大胜 | 【德国#9】4-2-3-1;已提前出线大幅轮换!鲍曼🅖替诺伊尔;施洛特贝克❌伤缺;穆西亚拉休息;上轮2-1科特迪瓦 | 🌍休斯顿NRG(72K) | 🔥德国放水 | H2H:首次交手", "home": "厄瓜多尔", "away": "德国", "result": "2:1", "ht_result": "1:1", "postMatch": "【6/26爆冷】厄瓜多尔2-1德国:萨内2分闪电破门;安古洛扳平;普拉塔77分绝杀!德国仍头名出线;厄瓜多尔最佳第三晋级", "source": "ai"}, {"id": 56, "spf": "待定", "tip": "负", "level": "🟢铁胆", "injury": "【库拉索#91】4-4-2;已出局;首分;上轮0-0厄瓜多尔 | 【科特迪瓦#37】4-3-3;阿莱🅕✅;凯西🅜✅;首战1-0厄瓜多尔+次轮0-2德国 | 🌍堪萨斯城(76K) | 🔥科特迪瓦争出线 | H2H:首次交手", "home": "库拉索", "away": "科特迪瓦", "score": "0:2/1:3", "htft": "负-负", "totalGoals": "3球/2球", "result": "0:2", "ht_result": "0:1", "postMatch": "【6/26】库拉索 0-2 科特迪瓦:库拉索出局;科特迪瓦4分最佳第三有望", "source": "template"}, {"id": 57, "spf": "待定", "tip": "平", "level": "🔵中等", "note": "日本vs瑞典-死亡之组终局", "injury": "【日本#14】4-2-3-1;久保建英🅜✅;堂安律🅕✅;三笘薰❌+南野❌+远藤航❌三核缺阵!残阵;上轮4-0突尼斯 | 【瑞典#25】4-4-2;伊萨克🅕✅;哲凯赖什🅕✅;上轮1-5惨败荷兰 | 🌍达拉斯AT&T(80K) | 🔥死亡之组终局 | H2H:近年瑞典占优", "totalGoals": "2球/3球", "htft": "平平/平-胜", "score": "1:1/2:2", "home": "日本", "away": "瑞典", "result": "1:1", "ht_result": "0:0", "postMatch": "【6/26】日本1-1瑞典:日本残阵逼平瑞典!小组第二出线!瑞典出局", "source": "ai"}, {"id": 58, "spf": "待定", "tip": "负", "level": "🟡稳胆", "totalGoals": "3球/2球", "htft": "负-负/平-负", "score": "0:2/1:3", "note": "荷兰vs突尼斯", "injury": "【突尼斯#50】4-3-3;已出局;上轮0-4日本 | 【荷兰#7】4-3-3;范戴克🅓✅;加克波🅕✅;廷贝尔❌+德利赫特❌防线残阵;上轮5-1屠瑞典 | 🌍蒙特雷(53K) | 🔥荷兰冲头名 | H2H:荷兰占优", "home": "突尼斯", "away": "荷兰", "result": "0:3", "ht_result": "0:2", "postMatch": "【6/26】突尼斯 0-3 荷兰:荷兰头名出线!加克波双响;突尼斯出局", "source": "ai"}, {"id": 59, "spf": "待定", "tip": "负", "level": "🟡稳胆", "note": "土耳其vs美国-D组头名战", "injury": "【土耳其#33】4-4-2;🅕队长;🅜组织核心;🅓防守核心 | 【美国#15】4-4-2;🅕✅核心可出战;🅜✅中场;🅓✅防线 | 🌍洛杉矶·SoFi体育场 | 🔥出线关键战 | H2H:待确认 | 上轮0:1 | 上轮2:0", "home": "土耳其", "away": "美国", "score": "0:1/0:2", "htft": "负-负/平-负", "totalGoals": "2球/1球", "result": "0:1", "ht_result": "0:0", "postMatch": "【6/26】土耳其 0-1 美国:美国轮换仍全胜9分D组头名!土耳其出局", "source": "template"}, {"id": 60, "spf": "待定", "tip": "负", "level": "🟡稳胆", "injury": "【巴拉圭#45】4-4-2;🅕队长;🅜组织核心;🅓防守核心 | 【澳大利亚#24】4-4-2;🅕✅核心可出战;🅜✅中场;🅓✅防线 | 🌍旧金山·Levi\\ | 🔥出线关键战 | H2H:待确认 | 上轮0:1 | 上轮2:0", "home": "巴拉圭", "away": "澳大利亚", "score": "0:1/0:2", "htft": "负-负/平-负", "totalGoals": "2球/1球", "result": "0:0", "ht_result": "0:0", "postMatch": "【6/26】巴拉圭0-0澳大利亚:澳大利亚4分D组第二出线!巴拉圭出局", "source": "template"}, {"id": 61, "spf": "4.50/4.15/1.50", "tip": "负", "level": "🟢铁胆", "note": "挪威vs法国-哈兰德vs姆巴佩", "injury": "【挪威#36】4-3-3;哈兰德🅕✅(3球);厄德高🅜✅;已4分小组头名;上轮2-0塞内加尔 | 【法国#2】4-2-3-1;姆巴佩🅕✅(2球);登贝莱🅕✅;已4分;上轮3-2伊拉克 | 🌍纽约大都会(82K) | 🔥I组头名之争!哈兰德vs姆巴佩 | H2H:近年法国占优", "home": "挪威", "away": "法国", "score": "0:1/0:2", "htft": "负-负/平-负", "totalGoals": "2球/1球", "code": "周五061", "result": "1:4", "ht_result": "1:3", "postMatch": "挪威 1:4 法国 | 登贝莱7/20/32帽子戏法(25分钟历史第二快),杜埃90+4破门;哈兰德+厄德高轮休未登场;挪威21阿斯特高一度扳平,50斯特兰德-拉森点球被迈尼昂扑出;法国9分小组头名挪威6分第二,两队携手晋级", "source": "ai"}, {"id": 62, "spf": "待定", "tip": "胜", "level": "🟢铁胆", "injury": "【塞内加尔#17】4-3-3;马内🅕✅;雅克松🅕;已1分;上轮0-2挪威 | 【伊拉克#68】4-4-2;侯赛因🅕;已0分出局;上轮2-3法国 | 🌍费城林肯(67K) | 🔥塞内加尔争出线 | H2H:首次交手", "home": "塞内加尔", "away": "伊拉克", "score": "2:0/1:0", "htft": "胜-胜/平-胜", "totalGoals": "2球/1球", "code": "周五062", "result": "5:0", "ht_result": "3:0", "postMatch": "塞内加尔 5:0 伊拉克 | 伊拉克13苏拉卡红牌(拉倒马内);迪亚拉4破门,萨尔56成塞内加尔世界杯射手王(4球),盖耶59/71双响,恩迪亚耶82;塞内加尔3分等最佳第三晋级,伊拉克0分出局", "source": "template"}, {"id": 63, "spf": "2.28/3.23/2.62", "tip": "胜", "level": "🟡稳胆", "injury": "【佛得角#72】4-4-2;🅕✅核心可出战;🅜✅中场;🅓✅防线 | 【沙特阿拉伯#48】5-4-1;🅕队长;🅜组织核心;🅓防守核心 | 🌍休斯顿·NRG体育场 | 🔥出线关键战 | H2H:待确认 | 上轮2:2 | 上轮4:0", "home": "佛得角", "away": "沙特阿拉伯", "score": "2:0/1:0", "htft": "胜-胜/平-胜", "totalGoals": "2球/1球", "code": "周五063", "result": "0:0", "ht_result": "1:0", "postMatch": "佛得角 0:0 沙特阿拉伯 | 佛得角门将沃济尼亚多次神扑当选全场最佳;塞梅多和努诺达科斯塔错失良机;佛得角3分小组第二创历史晋级32强(三场0:0/2:2/0:0),将对阵阿根廷;沙特2分出局", "source": "template"}, {"id": 64, "spf": "6.02/3.65/1.45", "tip": "负", "level": "🟠大概率", "note": "乌拉圭vs西班牙-H组冠军战", "injury": "【乌拉圭#11】3-4-3(贝尔萨);努涅斯🅕✅;巴尔韦德🅜✅;已2分;上轮2-2佛得角 | 【西班牙#3】4-3-3;亚马尔🅕✅(首球);罗德里🅜✅;已4分;上轮4-0沙特 | 🌍亚特兰大(71K) | 🔥西班牙争头名 | H2H:西班牙近年占优", "home": "乌拉圭", "away": "西班牙", "score": "0:1/0:2", "htft": "负-负/平-负", "totalGoals": "2球/1球", "code": "周五064", "result": "0:1", "ht_result": "0:0", "postMatch": "乌拉圭 0:1 西班牙 | 巴埃纳42远射,穆斯莱拉低级失误漏进球门(半场被换下);费兰托雷斯86中框;卡诺比奥90+4红牌;西班牙7分H组头名;乌拉圭2分出局,连续两届小组赛淘汰", "source": "ai"}, {"id": 65, "spf": "待定", "tip": "负", "level": "🟢铁胆", "totalGoals": "3球/4球", "htft": "负-负", "score": "0:3/0:4", "note": "比利时vs新西兰", "injury": "【新西兰#82】4-4-2;🅕队长;🅜组织核心;🅓防守核心 | 【比利时#8】4-2-3-1;🅕✅核心可出战;🅜✅中场;🅓✅防线 | 🌍温哥华·BC Place | 🔥出线关键战 | H2H:待确认 | 上轮2:2 | 上轮0:0", "home": "新西兰", "away": "比利时", "code": "周五066", "result": "1:5", "ht_result": "0:2", "postMatch": "新西兰 1:5 比利时 | 特罗萨德28/50双响,德布劳内66破门(比利时最年长世界杯进球者34岁),卢卡库86替补56秒破门(比利时世界杯射手王6球),萨勒马克尔斯90+4;贾斯特84扳回一球;比利时5分G组头名;新西兰1分出局", "source": "template"}, {"id": 66, "spf": "2.15/2.50/3.78", "tip": "胜", "level": "🟠大概率", "note": "埃及vs伊朗-出线关键战", "injury": "【埃及#28】4-2-3-1;🅕✅核心可出战;🅜✅中场;🅓✅防线 | 【伊朗#18】4-4-2;🅕队长;🅜组织核心;🅓防守核心 | 🌍西雅图·Lumen球场 | 🔥出线关键战 | H2H:待确认 | 上轮2:2 | 上轮0:0", "home": "埃及", "away": "伊朗", "score": "2:0/1:0", "htft": "胜-胜/平-胜", "totalGoals": "2球/1球", "code": "周五065", "result": "1:1", "ht_result": "1:0", "postMatch": "埃及 1:1 伊朗 | 埃及5萨贝尔首开纪录;伊朗10塔雷米点球被扑,14雷扎伊安补射扳平(伊朗世界杯射手王);90+3哈利勒扎德绝杀被VAR判越位无效;埃及5分小组第二晋级对澳大利亚;伊朗3分等最佳第三", "source": "template"}, {"id": 67, "spf": "待定", "tip": "负", "level": "🟢铁胆", "totalGoals": "2球/3球", "htft": "负-负/平-负", "score": "0:2/1:3", "note": "英格兰vs巴拿马", "injury": "【巴拿马#54】5-4-1;近2场0胜0平2负(进0失2);卡拉斯基利亚❌内收肌伤缺;戈多伊⚠️缺乏比赛体能仅替补1分钟;布莱克曼🅕队长;哈维🟡黄牌累计;巴拿马已淘汰求首球首胜 | 【英格兰#4】4-2-3-1;近2场1胜1平0负(进4失2);里斯詹姆斯❌腘绳肌伤缺(R32也存疑);赖斯✅恢复训练可出战;安德森✅恢复训练可出战;萨卡⚠️跟腱炎管理预计本届首秀;赖斯🟡黄牌停赛风险 | 🌍纽约大都会人寿(82K) | 🔥英格兰需胜确保头名避开葡萄牙 | H2H:1胜(英格兰6-1,2018世界杯) | 上轮0:1负克罗地亚 | 上轮0:0平加纳(78%控球无进球)", "home": "巴拿马", "away": "英格兰", "code": "周六068", "source": "ai", "result": "0:2", "postMatch": "巴拿马 0:2 英格兰 | 贝林厄姆62分角球破门(萨卡助攻),凯恩67分头球破11球超莱因克尔成英格兰世界杯射手王;巴拿马0分0进球出局;英格兰7分L组头名晋级对民主刚果"}, {"id": 68, "spf": "1.66/3.05/5.05", "tip": "胜", "level": "🟢铁胆", "injury": "【克罗地亚#10】4-2-3-1;近2场1胜0平1负(进3失4);全员健康无伤停;莫德里奇201场国家队出场史上第4人;佩里西奇20场世界杯首发;布迪米尔替补绝杀后预计首发;科瓦契奇🅜中场核心 | 【加纳#60】4-1-4-1;近2场1胜1平0负(进1失0);阿蒂齐吉❌腹股沟伤退出本届赛事;阿萨雷替补2场零封表现神勇;帕尔特伊✅健康坐镇中场;伊尼亚基威廉姆斯🟡+伊伦基🟡黄牌停赛风险;加纳平局即出线 | 🌍费城林肯金融球场(68K) | 🔥克罗地亚必胜战vs加纳钢铁防线2场零封 | H2H:首次交手 | 上轮1:0胜巴拿马布迪米尔54分绝杀 | 上轮0:0平英格兰仅2射门", "home": "克罗地亚", "away": "加纳", "score": "2:0/3:1", "htft": "胜-胜/平-胜", "totalGoals": "2球/3球", "code": "周六067", "source": "ai", "result": "2:1", "postMatch": "克罗地亚 2:1 加纳 | 苏契奇31分30码低射破门;加纳73分卢卡森VAR确认扳平;弗拉西奇83分莫德里奇角球助攻头球绝杀;克罗地亚6分小组第二;加纳4分最佳第三双双晋级"}, {"id": 69, "spf": "3.60/3.70/1.72", "tip": "负", "level": "🟠大概率", "note": "哥伦比亚vs葡萄牙-C罗小组终战", "injury": "【哥伦比亚#12】4-3-3;近2场2胜0平0负(进4失1);路易斯苏亚雷斯⚠️肩伤对民主刚果被换下预计首发;全员健康无停赛;J罗队长对民主刚果5次关键传球;路易斯迪亚斯🅕左路爆点;穆尼奥斯🅓连续2场破门 | 【葡萄牙#5】4-2-3-1;近2场1胜1平0负(进6失1);托马斯阿劳霍❌存疑首战受伤;鲁本迪亚斯✅伤愈回归首发;C罗✅首发6届世界杯10球975生涯进球;B费🅜组织核心;内托🅕右路突破 | 🌍迈阿密硬石体育场(65K) | 🔥小组头名争夺哥伦比亚平即头名葡萄牙必须赢 | H2H:首次交手仅2014友谊赛0:0 | 上轮1:0胜民主刚果穆尼奥斯76分制胜 | 上轮5:0胜乌兹别克C罗2球", "home": "哥伦比亚", "away": "葡萄牙", "score": "0:1/0:2", "htft": "负-负/平-负", "totalGoals": "1球/2球", "code": "周六069", "source": "ai", "result": "0:0", "postMatch": "哥伦比亚 0:0 葡萄牙 | 双方36射门(哥伦比亚24射创队史纪录);迪奥戈科斯塔多次神扑;戴文森桑切斯90+1头球绝杀被VAR判越位无效;哥伦比亚7分K组头名;葡萄牙5分小组第二"}, {"id": 70, "spf": "1.43/4.15/5.28", "tip": "胜", "level": "🔵中等", "injury": "【民主刚果#61】4-3-3;全员健康无停赛;德萨布尔教练放弃5后卫改打进攻433;维萨🅕唯一世界杯进球者;巴坎布🅕21国家队进球;姆本巴🅓防线领袖;万比萨卡🅓右路首发 | 【乌兹别克斯坦#58】3-4-2-1;马沙里波夫❌伤缺;哈姆罗别科夫🟡黄牌停赛风险;肖穆罗多夫🅕队长44国家队进球;库萨诺夫🅓曼城中卫防线核心;法伊祖拉耶夫🅕唯一世界杯进球者;乌兹别克近4场全败失12球 | 🌍亚特兰大梅赛德斯奔驰体育场(71K) | 🔥双方争最佳第三晋级:刚果需胜,乌兹别克需净胜球奇迹 | H2H:首次交手刚果对亚洲队2平4负不胜 | 上轮0:1负哥伦比亚 | 上轮0:5负葡萄牙", "home": "民主刚果", "away": "乌兹别克斯坦", "score": "2:0/3:1", "htft": "胜-胜/平-胜", "totalGoals": "2球/3球", "code": "周六070", "source": "ai", "result": "3:1", "postMatch": "民主刚果 3:1 乌兹别克斯坦 | 肖穆罗多夫10分吊射领先;维萨68分点球扳平;马耶莱78分补射反超;维萨90+1世界波锁定;民主刚果4分首次晋级32强对英格兰;乌兹别克0分出局"}, {"id": 71, "spf": "3.90/1.94/2.80", "tip": "平", "level": "🟡稳胆", "injury": "【阿尔及利亚#43】4-2-3-1;近2场1胜0平1负(进3失5);阿穆拉❌腘绳肌伤缺(首战对阿根廷受伤预选赛24球进10球核心);古伊里✅替补绝杀约旦后预计首发;本布阿利✅替补扳平约旦后预计首发中场;马赫雷斯🅜35岁第三次世界杯核心创造力;本塔莱布🅓防守中场首发 | 【奥地利#21】4-2-3-1;近2场1胜0平1负(进3失3);波施⚠️颚骨骨折戴面罩出战;阿拉巴⚠️膝盖管理出战;万纳❓存疑可能不登场;楚克维梅卡新归化球员首发首秀;阿瑙托维奇🅕37岁首度首发奥地利队史射手王47球;扎比策🅜队长 | 🌍堪萨斯城箭头体育场(76K) | 🔥1982世界杯奥地利2-0胜阿尔及利亚后默契球丑闻淘汰阿队44年复仇战 | H2H:1负(0-2,1982世界杯) | 上轮2:1胜约旦古伊里82分绝杀 | 上轮0:2负阿根廷", "home": "阿尔及利亚", "away": "奥地利", "score": "1:1/0:0", "htft": "负-负/平-负", "totalGoals": "1球/2球", "code": "周六071", "source": "ai", "result": "3:3", "postMatch": "阿尔及利亚 3:3 奥地利 | 阿瑙托维奇28分首开纪录;贝尔加利45分扳平;萨比策55分再超出;马赫雷斯60分扳平90+3双响绝杀;卡拉季奇90+6头球绝平;双方3-3双双晋级"}, {"id": 72, "spf": "待定", "tip": "负", "level": "🟢铁胆", "totalGoals": "2球/3球", "htft": "负-负/平-负", "score": "0:2/1:3", "note": "阿根廷vs约旦-梅西小组终战", "injury": "【约旦#64】3-4-3;近2场0胜0平2负(进2失5);全员健康无伤停;阿尔拉什丹🅜对阿尔及利亚进球;阿尔塔马里🅕法甲蒙彼利埃核心;约旦已淘汰但打入队史世界杯首球 | 【阿根廷#1】4-3-3;近2场2胜0平0负(进5失0);克里斯蒂安罗梅罗❌膝伤缺阵对奥地利亚军;奥塔门迪塞内西搭档利马中卫;梅西⚠️轮休预计下半场替补出场;阿尔瓦雷斯✅脚踝恢复首次首发;洛塞尔索帕雷德斯帕拉西奥斯轮换中场;大幅轮换备战16强 | 🌍达拉斯AT&T体育场(80K) | 🔥阿根廷已锁定J组头名约旦荣誉之战 | H2H:首次交手 | 上轮1:2负阿尔及利亚 | 上轮2:0胜奥地利梅西2球破纪录", "home": "约旦", "away": "阿根廷", "code": "周六072", "source": "ai", "result": "1:3", "postMatch": "约旦 1:3 阿根廷 | 洛塞尔索19分任意球破门;劳塔罗31分VAR点球;塔马里55分扳回一球;梅西60分替补登场80分任意球破门第6球;阿根廷9分J组头名;约旦出局"}, {"id": 73, "spf": "5.65/3.50/1.50", "tip": "负", "level": "🟠大概率", "note": "1/16决赛 A2vsB2", "home": "南非", "away": "加拿大", "score": "0:2/1:2", "htft": "负-负/平-负", "totalGoals": "2球/3球", "injury": "【南非#74】4-2-3-1;近3场1胜1平1负(进2失3);莫科埃纳✅黄牌停赛复出中场核心;兹瓦内❌3场停赛(红牌对墨西哥上诉失败);马塞科🅕对韩国制胜球;马戈帕🅕支点中锋;威廉姆斯🅖队长点球专家;布鲁斯74岁最后一站 | 【加拿大#29】4-4-2;近3场1胜1平1负(进8失3);科内❌断腿退出赛事;阿方索戴维斯⚠️腿筋(整个小组赛缺阵,最多替补);尤斯塔基奥⚠️肌肉伤赛前检测;阿爾菲琼斯⚠️存疑;乔纳森戴维🅕42球80场;拉林🅕双前锋;马什教练排攻击442 | 🌍洛杉矶SoFi体育场(70K) | 🔥两队皆首进淘汰赛:加拿大攻击力vs南非防守反击 | H2H:首次交手 | 上轮1:0胜韩国(马塞科63分) | 上轮1:2负瑞士", "source": "ai", "result": "0:1", "postMatch": "南非 0:1 加拿大 | 尤斯塔基奥90+2远射绝杀!南非55%控球但仅0.13xG;威廉姆斯多次神扑;加拿大历史首进16强;南非首次淘汰赛止步"}, {"id": 74, "spf": "待定", "tip": "胜", "level": "🟢铁胆", "home": "德国", "away": "巴拉圭", "score": "2:0/3:0", "htft": "胜-胜/平-胜", "totalGoals": "2球/3球", "injury": "【德国#9】4-2-3-1;近3场2胜0平1负(进10失4);施洛特贝克❌踝/膝韧带撕裂退出赛事;吕迪格替代首发;布朗⚠️内收肌伤(错过厄瓜多尔,预计恢复);穆西亚拉+维尔茨⚠️状态未达巅峰(克罗斯公开警告须点燃创造力火花否则出局);恩梅查+帕夫洛维奇双后腰;哈弗茨🅕首发中锋;翁达夫🅜超级替补3球(均替补)全队射手王 | 【巴拉圭#45】4-5-1;近3场1胜1平1负(进1失4);迭戈戈麦斯❌停赛(一场);阿尔德雷特⚠️膝伤存疑;阿尔米隆⚠️(红牌停赛vs土耳其,需确认是否回归);恩西索🅜进攻核心;萨纳布里亚🅕单箭头;连续2场零封(1-0土耳其/0-0澳大利亚)防守韧性极强 | 🌍波士顿吉列体育场(65K) | 🔥德国12年来首场淘汰赛(2018/2022连续小组出局);克罗斯警告\"必须难缠\" | H2H:2战德国1胜1平(2002世界杯德国1-0;2013友谊赛3-3) | 上轮1:2负厄瓜多尔 | 上轮0:0平澳大利亚", "source": "ai", "code": "周一075", "result": "1:1", "postMatch": "德国 1:1 巴拉圭 | 巴拉圭42分恩西索头球领先;德国54分哈弗茨头球扳平;加时102分塔头球破门被VAR判犯规取消;点球大战德国哈弗茨+沃尔特马德+塔罚丢,巴拉圭4-3晋级!德国92年来首次世界杯点球出局"}, {"id": 75, "spf": "待定", "tip": "胜", "level": "🟠大概率", "home": "荷兰", "away": "摩洛哥", "score": "2:1/1:1", "htft": "胜-胜/平-胜", "totalGoals": "2球/3球", "injury": "【荷兰#7】4-3-3;近3场2胜1平0负(进10失4);邓弗里斯✅+布罗比✅轻伤已恢复;范德文左后卫复出;范戴克🅓队长;格拉文贝赫🅜;加克波🅕;德容🅜组织核心;荷兰连续7场无零封防守存疑 | 【摩洛哥#6】4-2-3-1;近3场2胜1平0负(进6失3);全员健康无停赛;马兹拉维轮休后回归;布阿迪轮休后回归;乌纳希回归首发;赛巴里🅕3场3球(拜仁签入)队内射手王;阿什拉夫🅓边路最大威胁(科曼点名盯防);布努🅖;摩洛哥FIFA排名第6高于荷兰第7 | 🌍蒙特雷BBVA体育场(53K) | 🔥荷摩文化战:43万摩洛哥裔在荷兰,3名荷兰出生球员效力摩洛哥 | H2H:3战荷兰2胜1负(1994世界杯荷兰2-1,科曼出场) | 上轮3:1胜突尼斯 | 上轮4:2胜海地", "source": "ai", "code": "周一076", "result": "1:1", "postMatch": "荷兰 1:1 摩洛哥 | 加克波下半场破门;摩洛哥伤停补时绝平!加时无果;点球大战摩洛哥4-3胜!荷兰连续7场无零封魔咒继续;摩洛哥历史性晋级16强对加拿大"}, {"id": 76, "spf": "待定", "tip": "胜", "level": "🟢铁胆", "home": "巴西", "away": "日本", "score": "2:0/3:1", "htft": "胜-胜/平-胜", "totalGoals": "2球/3球", "injury": "【巴西#6】4-3-3;近3场2胜1平0负(进8失2);拉菲尼亚❌右腿筋撕裂确认缺阵;拉扬🅕首发替换;内马尔✅伤愈(ACL缺阵981天后对苏格兰替补复出76分钟,安切洛蒂确认可首发或打满90分钟);维尼修斯✅4球3场(自2002年大罗+里瓦尔多后首位场场进球巴西球员);库尼亚🅕首发中锋;吉马良斯🅜中场;马尔基尼奥斯🅓队长 | 【日本#14】3-4-2-1;近3场1胜2平0负(进3失2);久保建英⚠️存疑(攻击中场可能部分出场);板仓滉⚠️带伤预计首发;南野拓实❌受伤未入名单(但随队支持);23/26球员效力欧洲顶级联赛;上田绮世🅕(费耶诺德);三笘薰🅕主力;远藤航🅜队长;日本曾3-2客胜巴西(2025友谊赛) | 🌍休斯顿NRG体育场(72K) | 🔥内马尔vs日本克星:5战9球含大四喜(2014),日本称其为\"天敌\" | H2H:5战巴西3胜1平1负(内马尔9球;2006世界杯巴西4-1;2025日本3-2胜) | 上轮3:0胜苏格兰 | 上轮1:1平瑞典", "source": "ai", "code": "周一074", "result": "2:1", "postMatch": "巴西 2:1 日本 | 日本29分佐野海舟首球;巴西56分卡塞米罗头球扳平;90+5马丁内利绝杀!安切洛蒂半场换上恩德里克改变战局;巴西晋级16强对摩洛哥;日本0胜淘汰赛出局"}, {"id": 77, "spf": "1.16/5.80/10.50", "tip": "胜", "level": "🟢铁胆", "home": "法国", "away": "瑞典", "score": "2:0/3:0", "htft": "胜-胜/平-胜", "totalGoals": "2球/3球", "injury": "【法国#2】4-3-3;近3场3胜0平0负(进10失2);全员健康无伤停;德尚归队(母亲葬礼后返回);姆巴佩✅4球3场(百场国家队里程碑);登贝莱✅半场帽子戏法(1994来首人);姆巴佩+登贝莱组合5球(世界杯史上第3对);奥利塞🅜创造核心;科内🅜中场主力;楚阿梅尼/卡马文加/拉比奥轮换三中场 | 【瑞典#25】4-2-3-1;近3场1胜1平1负(进7失7);伊萨克希恩❌伤缺(防线重创,已失7球3场);哲凯赖什✅(葡体射手,顶级威胁);伊萨克🅕(利物浦,与哲凯赖什组成强袭组合);埃兰加🅕2球近6场;库卢塞夫斯基🅜创造力;福斯贝里🅜经验;瑞典连续10场无零封,BTTS率90% | 🌍纽约大都会人寿(82K) | 🔥世界冠军vs格兰姆波特梦想之战:法国三叉戟尚未同时爆发 | H2H:8战法国5胜1平2负(最近1993法国1-0) | 上轮4:1胜挪威(登贝莱帽子戏法) | 上轮1:1平日本", "source": "ai", "code": "周二078", "result": "3:0", "postMatch": "法国 3:0 瑞典 | 姆巴佩45/74双响(世界杯淘汰赛进球纪录);巴尔科拉53分奥利塞助攻;法国3-0碾压瑞典;瑞典零射正;法国晋级16强对巴拉圭"}, {"id": 78, "spf": "3.60/3.38/1.80", "tip": "负", "level": "🟡稳胆", "home": "科特迪瓦", "away": "挪威", "score": "1:2/0:1", "htft": "负-负/平-负", "totalGoals": "1球/2球", "injury": "【科特迪瓦#50】4-3-3;近3场2胜0平1负(进3失2);全员健康无停赛;佩佩🅕2球状态佳;迪亚洛🅕曼联边锋;凯西🅜中场核心;桑加雷🅜防守中场;科索努🅓+迪奥曼德🅓中卫组合对抗哈兰德;科特迪瓦首进淘汰赛(近5场4胜含法国);反击犀利 | 【挪威#36】4-3-3;近3场2胜0平1负(进8失6);哈兰德✅(对法国轮休满体力,4球金靴竞争者仅次于梅西5球);厄德高✅(对法国轮休,组织核心);努萨✅(莱比锡\"挪威内马尔\");索尔洛特✅轮休;里尔森✅轮休;索尔巴肯对法国轮换10人为保存体力;挪威进攻12球3场但防守漏6球 | 🌍达拉斯AT&T体育场(80K) | 🔥哈兰德vs非洲铁壁:科索努+迪奥曼德双中卫能否锁死金靴热门 | H2H:首次交手 | 上轮2:0胜库拉索 | 上轮1:4负法国(轮换10人)", "source": "ai", "code": "周二077", "result": "1:2", "postMatch": "科特迪瓦 1:2 挪威 | 努萨39分远射首开纪录;阿马德迪亚洛74分个人能力扳平;哈兰德86分制胜球!挪威2-1晋级16强对巴西"}, {"id": 79, "spf": "待定", "tip": "胜", "level": "🟡稳胆", "home": "墨西哥", "away": "厄瓜多尔", "score": "1:0/2:0", "htft": "胜-胜/平-胜", "totalGoals": "1球/2球", "injury": "【墨西哥🇲🇽#16】4-3-3;近3场3胜0平0负(进5失0);全员健康✅无停赛;6连胜+11场不败;奥乔亚40岁6届世界杯;莫拉🅜17岁新星;希门尼斯🅕首发破门;阿兹特克高原2240m主场(仅1负);墨西哥3场零封创队史;基尼奥内斯🅕速度爆点 | 【厄瓜多尔🇪🇨#40】4-4-2;全员健康✅;凯塞多🅜切尔西中场核心;安古洛🅕3球近6场;瓦伦西亚🅕队长;因卡皮耶🅓阿森纳;小组赛0:0/0:0后爆冷2-1胜德国;16场仅1负 | 🌍墨西哥城高原主场 | 🔥墨西哥破除40年淘汰赛魔咒", "source": "ai", "code": "周二079", "result": "2:0", "postMatch": "墨西哥 2:0 厄瓜多尔 | 基尼奥内斯22分内切爆射上角;希门尼斯31分禁区外劲射;墨西哥4场零封创纪录!40年首进16强;厄瓜多尔因卡皮耶90+5红牌;墨西哥晋级对英格兰"}, {"id": 80, "spf": "待定", "tip": "胜", "level": "🟢铁胆", "home": "英格兰", "away": "民主刚果", "score": "2:0/3:0", "htft": "胜-胜/平-胜", "totalGoals": "2球/3球", "injury": "【英格兰🏴󠁧󠁢󠁥󠁮󠁧󠁿#4】4-2-3-1;近3场2胜1平0负(进6失2);宽萨❌脚踝扭伤缺阵;里斯詹姆斯❌腘绳肌缺阵;利夫拉门托❌小腿退出赛事;斯彭斯首发右后卫(首次世界杯淘汰赛先发);赖斯✅轮休后满状态回归;贝林厄姆✅10号位核心;萨卡✅(跟腱管理);拉什福德✅左翼;凯恩✅11球英格兰世界杯射手王;安德森🅜搭档赖斯双后腰; Konsa+Guehi中卫组合 | 【民主刚果🇨🇩#46】5-3-2防反;全员健康✅无停赛;德萨布尔改打532防守反击;维萨🅕3球纽卡前锋状态火爆;巴坎布🅕35岁经验丰富;万比萨卡🅓+图安泽贝🅓原英格兰青训;姆本巴🅓防线领袖 | 🌍亚特兰大梅赛德斯奔驰体育场 | 🔥图赫尔:必须找到解决方案", "source": "ai", "code": "周三080", "result": "2:1", "postMatch": "英格兰 2:1 民主刚果 | 民主刚果7分闪电破门;凯恩75分扳平+86分头球绝杀双响!英格兰60年来首次世界杯逆转胜;刚果虽败犹荣;英格兰晋级16强对墨西哥"}, {"id": 81, "spf": "待定", "tip": "胜", "level": "🟢铁胆", "home": "美国", "away": "波黑", "score": "2:0/3:1", "htft": "胜-胜/平-胜", "totalGoals": "2球/3球", "injury": "【美国🇺🇸#15】4-3-3;近3场2胜0平1负(进9失3);普利西奇✅小腿伤愈确认首发(对土耳其替补出场后训练完整);巴洛贡✅回归首发(2球1助,1930年来首位单届多球美国球员);亚当斯✅轮休后满状态;麦肯尼🅜首发;罗宾逊✅理查兹✅全部可用;德斯特🅓右路爆点;麦肯齐⚠️脚伤存疑;特拉斯蒂⚠️脚踝存疑;罗尔丹⚠️肌肉伤0出场;弗里泽🅖首发门将;波切蒂诺排433进攻阵型;美国2002年来未赢过淘汰赛 | 【波黑🇧🇦#64】4-4-2;近3场1胜1平1负(进5失6);哲科✅40岁150场73球出战;穆哈雷莫维奇✅解禁复出(红牌后回归);德迪奇⚠️大腿伤存疑;德米罗维奇🅕(斯图加特)首发;巴伊拉塔雷维奇🅜(威斯康星出生,原美国青训,2024转投波黑);阿拉伊贝戈维奇🅜18岁勒沃库森新星;波黑首次世界杯淘汰赛;46次犯规小组第1 | 🌍旧金山李维斯体育场 | 🔥波切蒂诺:对我们来说这就是决赛", "source": "ai", "code": "周三082", "result": "2:0", "postMatch": "美国 2:0 波黑 | 美国2-0波黑:普利西奇首发建功;美国虽10人应战仍轻松取胜;晋级16强对比利时"}, {"id": 82, "spf": "待定", "tip": "胜", "level": "🟡稳胆", "home": "比利时", "away": "塞内加尔", "score": "2:0/1:0", "htft": "胜-胜/平-胜", "totalGoals": "1球/2球", "injury": "【比利时🇧🇪#9】4-2-3-1;近3场1胜2平0负(进5失1);恩戈伊✅红牌停赛期满回归;德巴斯特⚠️大腿伤部分训练存疑;德布劳内✅34岁最后一届世界杯(对新西兰1球全场最佳);特罗萨德✅2球状态火爆;卢卡库⚠️伤病管理(超级替补角色,对新西兰替补进球);多库✅缺席第2轮后满血回归;德凯特拉雷可能首发伪9号;库尔图瓦🅖;蒂勒曼斯🅜队长;黄金一代谢幕战;加西亚麾下16场不败 | 【塞内加尔🇸🇳#50】4-3-3;近3场1胜0平2负(进8失6);门迪❌膝伤退出赛事(对挪威伤退,已回俱乐部治疗);迪奥🅖首发出战(对伊拉克首秀);库利巴利⚠️速度下滑存疑(塞克可能替代);帕佩盖耶🔥替补双响对伊拉克冲击首发;马内🅕127场队长;萨尔🅕速度反击;杰克逊🅕支点;伊拉克5-0创非洲历史 | 🌍西雅图体育场 | 🔥首次交手!本届最均衡对决", "source": "ai", "code": "周三081", "result": "2:2", "postMatch": "比利时 2:2 塞内加尔 | 90分钟2-2平;德布劳内加时制胜3-2;比利时黄金一代挺进16强对USA;塞内加尔虽败犹荣"}, {"id": 83, "spf": "待定", "tip": "胜", "level": "🟠大概率", "home": "葡萄牙", "away": "克罗地亚", "score": "2:1/1:0", "htft": "胜-胜/平-胜", "totalGoals": "2球/3球", "injury": "【葡萄牙🇵🇹#5】4-2-3-1;近3场1胜2平0负(进6失1);全员健康✅无伤停!;C罗✅41岁6届世界杯10球(首破6届进球纪录);B费🅜组织核心;内托🅕右翼;若昂内维斯🅜回归首发(对哥伦比亚替补);莱奥🅕冲击首发位置;迪奥戈科斯塔🅖对哥伦比亚6次扑救MVP;鲁本迪亚斯✅防线核心;菲利克斯🅕首发;小组赛2场零进球遭葡媒批评后回暖 | 【克罗地亚🇭🇷#10】4-2-3-1;近3场2胜0平1负(进5失5);全员健康✅无伤停!;莫德里奇40岁第5届世界杯(21场连续出场,对加纳角球助攻史上最年长助攻者);格瓦迪奥尔🅓轮休后回归首发(佩里西奇推至左翼);布迪米尔🅕首发中锋;科瓦契奇🅜;斯塔尼希奇🅓;苏塔洛🅓;葡萄牙从未正式比赛负于克罗地亚(7胜2平1负) | 🌍多伦多BMO球场 | H2H:首次交手 | 🔥C罗vs莫德里奇:最后之舞", "source": "ai", "code": "周四084", "result": "2:1", "postMatch": "葡萄牙 2:1 克罗地亚 | 佩里西奇53分破门;C罗68分点球破世界杯淘汰赛首球!;贡萨洛拉莫斯90+4绝杀!克罗地亚3球被VAR吹掉;葡萄牙晋级16强对西班牙"}, {"id": 84, "spf": "待定", "tip": "胜", "level": "🟡稳胆", "home": "西班牙", "away": "奥地利", "score": "1:0/2:0", "htft": "胜-胜/平-胜", "totalGoals": "1球/2球", "injury": "【西班牙🇪🇸#3】4-3-3;近3场2胜1平0负(进5失0);尼科威廉姆斯❌内收肌拉伤确认缺阵(无撕裂,如晋级R16可回归);耶雷米皮诺❌肩关节扭伤确认缺阵!;维克托穆尼奥斯⚠️腘绳肌恢复完整训练(利物浦新援有望首秀);亚马尔✅腿筋管理可打满90分钟(唯一专职边锋);西班牙两翼全伤!巴埃纳将首发左边锋;罗德里🅜中场核心;佩德里🅜;奥亚萨瓦尔🅕中锋;西班牙0失球防线创历史但两翼伤兵满营;德拉富恩特承认可能无翼而战 | 【奥地利🇦🇹#21】4-2-3-1;近3场2胜0平1负(进6失4);阿拉巴⚠️对阿尔及利亚带伤出战成疑;阿瑙托维奇⚠️同样带伤存疑;波施✅戴定制护具出战(对约旦下颚骨折);卡拉季季奇✅96分钟绝平阿尔及利亚超级替补;萨比策🅜队长;莱默🅜;施拉格尔🅖;朗尼克高压体系;奥地利1954年来首次淘汰赛 | 🌍洛杉矶SoFi体育场 | H2H:首次交手 | 🔥西班牙边锋危机vs奥地利高压", "source": "ai", "code": "周四083", "result": "3:0", "postMatch": "西班牙 3:0 奥地利 | 奥亚萨瓦尔36/89双响(9.2分全场最佳);波罗65分破门;西班牙65%控球13射碾压;奥地利0射正;西班牙晋级16强"}, {"id": 85, "spf": "待定", "tip": "胜", "level": "🟡稳胆", "home": "瑞士", "away": "阿尔及利亚", "score": "2:0/1:0", "htft": "胜-胜/平-胜", "totalGoals": "1球/2球", "injury": "【瑞士🇨🇭#19】4-2-3-1;近3场2胜1平0负(进7失3);维德默⚠️臀部不适缺训存疑(雅凯可能替代);穆海姆⚠️存疑;扎卡🅜队长(勒沃库森核心);恩博洛🅕首发;阿坎吉🅓防线领袖;曼赞比🅕超级替补3球1助赛事爆发;瓦尔加斯🅜进球;瑞士防守纪律严明+定位球威胁;9场不败;仅1负近10场 | 【阿尔及利亚🇩🇿#43】4-3-3;近3场1胜1平1负(进5失7);阿穆拉❌确认缺阵(大腿拉伤恢复训练但未达标,预选赛头号射手);马赫雷斯✅35岁(对奥地利双响绝平,体力谨慎管理);古伊里✅首发中锋;本塞拜尼🅓;奥亚尔🅜2助;本塔莱布🅜;佩特科维奇面对旧主瑞士(曾执教7年!);7失球防守最差;H2H:瑞士7胜4平3负 | 🌍温哥华BC Place | 🔥佩特科维奇vs旧主:知己知彼", "source": "ai", "code": "周四085", "result": "2:0", "postMatch": "瑞士 2:0 阿尔及利亚 | 恩博洛11分+恩多耶46分;88年首胜淘汰赛"}, {"id": 86, "spf": "待定", "tip": "胜", "level": "🟢铁胆", "home": "阿根廷", "away": "佛得角", "score": "2:1/1:0", "htft": "胜-胜/平-胜", "totalGoals": "2球/1球", "injury": "【阿根廷🇦🇷#1】4-3-3;近3场3胜0平0负(进8失1);梅西✅轮休后满状态回归首发(小组赛6球,世界杯19球历史射手王!);罗梅罗⚠️膝伤管理(对奥地利后不适,奥塔门迪待命);蒙铁尔⚠️肌肉过载存疑;塔利亚菲科✅恢复首发左后卫;全员轮换后满体力;洛塞尔索🅜任意球破门状态佳;劳塔罗🅕点球破门;阿尔瓦雷斯🅕首发;迪布马丁内斯🅖2场零封;斯卡洛尼对约旦轮换9人;德保罗🅜+恩佐🅜+麦卡利斯特🅜中场铁三角 | 【佛得角🇨🇻#72】4-4-2;近3场0胜3平0负(进2失2);全员健康无伤停;沃济尼亚🅖40+岁门神2场零封(对西班牙/沙特);瑞安门德斯🅕队长;小组赛0-0逼平西班牙!2-2平乌拉圭!;历史上最小人口国家进入淘汰赛;紧凑防守+反击 | 🌍迈阿密Hard Rock体育场(准阿根廷主场) | H2H:首次交手 | 🔥世界杯史上最大实力差距对决?", "source": "ai", "code": "周五087", "result": "3:2", "postMatch": "阿根廷 3:2 佛得角 | 梅西29分破门创纪录;佛得角59分杜阿尔特扳平;利马92分加时破门;佛得角103分卡布拉尔再扳平!;罗梅罗111分乌龙折射绝杀;阿根廷120分钟险胜晋级"}, {"id": 87, "spf": "待定", "tip": "胜", "level": "🟡稳胆", "home": "哥伦比亚", "away": "加纳", "score": "1:0/2:0", "htft": "胜-胜/平-胜", "totalGoals": "1球/2球", "injury": "【哥伦比亚🇨🇴#12】4-3-3;近3场2胜1平0负(进4失1);全员健康✅无停赛!;迪亚斯🅕左翼爆点(1球1助,对葡萄牙后恢复良好);J罗🅜队长(11场世界杯6球4助,对葡萄牙5次关键传球);穆尼奥斯🅓连续2场破门;戴文森桑切斯🅓防线核心;科尔多瓦🅕替代苏亚雷斯首发(苏亚雷斯0.03xG低迷);莱尔马🅜防守中场;1失球小组最强防守;对葡萄牙24射创队史世界杯纪录 | 【加纳🇬🇭#60】4-1-4-1;近3场1胜1平1负(进3失2);库杜斯❌伤缺整个赛事(最大损失!);阿蒂齐吉⚠️小伤存疑(阿萨雷🅖替补2场零封);帕尔特伊✅法律问题解决可出战(前阿森纳,现比利亚雷亚尔);塞梅尼奥✅轻伤确认可出战;乔丹阿尤🅕首发;奎罗斯(前哥伦比亚主帅)面对旧主! | 🌍堪萨斯城Arrowhead体育场 | H2H:首次交手 | 🔥奎罗斯vs旧主+迪亚斯vs帕尔特伊:2022年那次铲球恩怨", "source": "ai", "code": "周五088", "result": "1:0", "postMatch": "哥伦比亚 1:0 加纳 | 约翰阿里亚斯16分制胜球;哥伦比亚防守铁壁再零封对手;加纳顽强但未破门;哥伦比亚晋级16强"}, {"id": 88, "spf": "待定", "tip": "负", "level": "🔵中等", "home": "澳大利亚", "away": "埃及", "score": "0:1/1:2", "htft": "平-负/负-负", "totalGoals": "1球/0球", "injury": "【澳大利亚🇦🇺#24】4-3-3;近3场1胜1平1负(进2失2);莱基❌腘绳肌退出赛事;伊塔利亚诺❌腹股沟退出赛事;阵容缩减至24人!;休息8天体能充沛;伊兰昆达🅕(20岁对土耳其进球);苏塔🅓(1.98m头球威胁);古德温🅕;博伊尔🅕;博斯🅓左后卫面对萨拉赫;瑞恩🅖100+场;已成功封锁居勒尔/伊尔迪兹/恩西索;波波维奇针对性部署 | 【埃及🇪🇬#28】4-2-3-1;近3场1胜2平0负(进5失4);萨拉赫⚠️左腿腘绳肌拉伤(对伊朗57分被换冰敷,扫描确认拉伤,已恢复部分训练,本人社媒发文OK!出战成疑);法图❌腘绳肌撕裂确认缺阵;阿卜杜勒莫内姆⚠️脚踝严重淤血(ACL后首战仅14分钟即下场,正加速恢复);拉申❌停赛缺阵;马尔穆什🅕曼城前锋;特雷泽盖🅕;埃及首次进入淘汰赛历史突破 | 🌍达拉斯AT&T体育场 | H2H:首次交手 | 🔥萨拉赫能否出战成最大悬念", "source": "ai", "code": "周五086", "result": "1:1", "postMatch": "澳大利亚 1:1 埃及 | 常规1-1平;加时无果;点球4-2埃及胜!;萨拉赫带伤出战送出助攻;澳大利亚虽败犹荣;埃及首进16强"}, {"id": 89, "spf": "待定", "tip": "平", "level": "🟡稳胆", "note": "1/8决赛", "home": "加拿大", "away": "摩洛哥", "injury": "【加拿大#29】4-2-3-1;🅕队长;🅜组织核心;🅓防守核心;近3场1胜1平1负(进8失3) | 【巴拉圭#45】5-4-1;🅕✅核心可出战;🅜✅中场;🅓✅防线;近3场1胜1平1负(进2失4) | 🌍费城·林肯金融球场 | 🔥出线关键战 | H2H:待确认 | 上轮2:1负瑞士 | 上轮0:0平澳大利亚", "score": "2:2/1:1", "htft": "平平/平-平", "totalGoals": "4球/3球", "source": "template", "result": "0:3", "postMatch": "加拿大 0:3 摩洛哥 | 摩洛哥 3:0 加拿大 | 乌纳希50/82双响;拉希米90+8补刀;加拿大东道主首支出局;摩洛哥强势晋级8强"}, {"id": 90, "spf": "待定", "tip": "平", "level": "🟠大概率", "home": "巴西", "away": "摩洛哥", "injury": "【巴西#6】4-3-3;近3场2胜1平0负(进8失2);帕克塔❌大腿肌肉二级拉伤缺阵(3周+);拉菲尼亚❌腿筋未风险复出(单独训练);卡塞米罗⚠️大腿痉挛(轻伤预计可出战);内马尔✅恢复可替补(仅14分钟出场);拉扬🅕19岁伯恩茅斯首发右翼;维尼修斯✅4球领衔;挪威4次交手从未取胜(2平2负含1998世界杯1-2) | 【挪威#36】4-3-3;近3场2胜0平1负(进8失6);里尔森⚠️大腿存疑(<50%概率出战);哈兰德✅场场进球(4+1球)领跑金靴;厄德高✅创造力核心;索尔洛特✅努萨✅全员出战;战术:中位拦截+长传哈兰德反击;巴西高点防线需警惕 | 🌍纽约大都会人寿(82K) | 🔥巴西从未赢过挪威(0胜2平2负)!哈兰德场场破门vs巴西残阵中场 | H2H:挪威2胜2平(1998世界杯挪威2-1) | 上轮2:1胜日本(马丁内利绝杀) | 上轮2:1胜科特迪瓦(哈兰德86分制胜)", "score": "3:3/1:1", "htft": "平平/平-平", "totalGoals": "6球/5球", "source": "ai", "result": "1:2", "postMatch": "巴西 1:2 挪威 | 哈兰德79/90双响绝杀!;内马尔终场前点球挽回颜面;吉马良斯失点;挪威首进世界杯8强!;巴西5战挪威0胜(2平3负)历史魔咒延续"}, {"id": 91, "spf": "待定", "tip": "平", "level": "🟢铁胆", "home": "法国", "away": "巴拉圭", "injury": "【法国#2】4-3-3;🅕队长;🅜组织核心;🅓防守核心;近3场3胜0平0负(进10失2) | 【巴拉圭#45】5-4-1;🅕✅核心可出战;🅜✅中场;🅓✅防线;近3场1胜1平1负(进2失4) | 🌍纽约·大都会人寿体育场 | 🔥出线关键战 | H2H:待确认 | 上轮1:4胜挪威 | 上轮0:0平澳大利亚", "score": "4:4/1:1", "htft": "平平/平-平", "totalGoals": "8球/7球", "source": "template"}, {"id": 92, "spf": "待定", "tip": "负", "level": "🟠大概率", "home": "墨西哥", "away": "英格兰", "injury": "【墨西哥#16】4-3-3;近4场4胜0平0负(进7失0);4场零封创纪录!;全员健康无停赛;基尼奥内斯🅕状态火(对厄瓜多尔破门);希门尼斯🅕;莫拉🅜18岁新星;阿兹特克海拔2240m主场87000人;墨西哥13年主场不败 | 【英格兰#4】4-2-3-1;近3场2胜1平0负(进6失2);里斯詹姆斯❌退出;宽萨❌脚踝伤缺;斯彭斯右后卫;奥莱利左后卫;萨卡✅+赖斯✅训练全勤;凯恩⚠️高原体能存疑(对刚果明显疲劳);海拔2240m极大考验英格兰双后腰:60分钟后压迫力骤降 | 🌍墨西哥城阿兹特克(87K,2240m) | 🔥高原堡垒vs三狮:墨西哥4场零封vs英格兰右后卫危机+海拔考验 | H2H:首次世界杯交手 | 上轮2:0胜厄瓜多尔 | 上轮2:1胜民主刚果(凯恩双响)", "score": "2:3/1:2", "htft": "负-负/平-负", "totalGoals": "5球/4球", "source": "ai", "code": "周日092", "result": "3:2", "postMatch": "英格兰 3:2 墨西哥 | 贝林厄姆36/38双响闪电战!;凯恩点球3-1;希门尼斯+基尼奥内斯扳回2球;墨西哥4场零封纪录终结;英格兰晋级8强对挪威"}, {"id": 93, "spf": "待定", "tip": "平", "level": "🔵中等", "home": "美国", "away": "比利时", "injury": "【R32-82胜者#50】4-4-2;🅕队长;🅜组织核心;🅓防守核心;首战 | 【R32-81胜者#50】5-4-1;🅕✅核心可出战;🅜✅中场;🅓✅防线;首战 | 🌍达拉斯·AT&T体育场 | 🔥出线关键战 | H2H:待确认 | 首战 | 首战", "score": "1:1/0:0", "htft": "平平/平-平", "totalGoals": "2球/1球", "source": "template", "result": "4:1", "postMatch": "比利时 4:1 美国 | 德凯特拉雷9/33双响!;蒂尔曼31任意球扳平56秒后遭反超;范纳肯57+卢卡库90+3;比利时黄金一代挺进8强"}, {"id": 94, "spf": "待定", "tip": "平", "level": "🟠大概率", "home": "西班牙", "away": "葡萄牙", "injury": "【西班牙#3】4-3-3;🅕队长;🅜组织核心;🅓防守核心;近3场2胜1平0负(进5失0) | 【葡萄牙#5】4-2-3-1;🅕✅核心可出战;🅜✅中场;🅓✅防线;近3场1胜2平0负(进6失1) | 🌍西雅图·Lumen球场 | 🔥出线关键战 | H2H:待确认 | 上轮0:1胜乌拉圭 | 上轮0:0平哥伦比亚", "score": "2:2/1:1", "htft": "平平/平-平", "totalGoals": "4球/3球", "source": "template", "result": "1:0", "postMatch": "西班牙 1:0 葡萄牙 | 梅里诺90+1绝杀!;罗德里助攻费兰再传中;C罗世界杯梦碎;西班牙晋级8强"}, {"id": 95, "spf": "1.22/4.72/10.25", "tip": "胜", "level": "🟢铁胆", "home": "阿根廷", "away": "埃及", "injury": "【阿根廷#1】4-3-3;🅕✅核心可出战;🅜✅中场;🅓✅防线;近3场3胜0平0负(进8失1) | 【埃及#28】4-4-2;🅕队长;🅜组织核心;🅓防守核心;近3场0胜3平0负(进4失4) | 🌍亚特兰大·梅赛德斯-奔驰体育场 | 🔥出线关键战 | H2H:待确认 | 上轮1:3胜约旦 | 上轮1:1平伊朗", "score": "3:1/2:0", "htft": "胜-胜/平-胜", "totalGoals": "4球/3球", "source": "template", "code": "周二095"}, {"id": 96, "spf": "待定", "tip": "平", "level": "🔵中等", "home": "哥伦比亚", "away": "瑞士", "injury": "【哥伦比亚#12】4-2-3-1;🅕队长;🅜组织核心;🅓防守核心;近3场2胜1平0负(进4失1) | 【瑞士#19】4-4-2;🅕✅核心可出战;🅜✅中场;🅓✅防线;近3场2胜1平0负(进7失3) | 🌍温哥华·BC Place | 🔥出线关键战 | H2H:待确认 | 上轮0:0平葡萄牙 | 上轮2:1胜加拿大", "score": "2:2/1:1", "htft": "平平/平-平", "totalGoals": "4球/3球", "source": "template"}, {"id": 97, "spf": "待定", "tip": "平", "level": "🟢铁胆", "note": "1/4决赛", "home": "法国", "away": "巴拉圭", "injury": "【法国#2】4-3-3;近5场5胜0平0负(进14失2);楚阿梅尼⚠️内收肌伤单独训练(出战存疑);科内替代首发;图拉姆⚠️小腿恢复部分训练(替补);姆巴佩✅7球金靴领跑(5场7球);登贝莱✅4球;7主力对巴拉圭后轮休仅预防性理疗无警报 | 【摩洛哥#13】4-2-3-1;近5场3胜1平1负(进9失3);赛巴里⚠️对加拿大肌肉伤检测中(严重度不高);里亚德✅膝盖预防性休战(复出);布努🅖;阿什拉夫🅓vs姆巴佩(前PSG队友对位);乌纳希🅜对加拿大双响状态火;拉希米🅕;34场国际赛不败 | 🌍波士顿吉列体育场(66K) | 🔥2022世界杯半决赛重演(法国2-0) | H2H:6战法国4胜1平1负 | 上轮1:0胜巴拉圭 | 上轮3:0胜加拿大", "score": "4:4/1:1", "htft": "平平/平-平", "totalGoals": "8球/7球", "source": "ai"}, {"id": 98, "spf": "1.55/3.68/4.70", "tip": "胜", "level": "🔵中等", "home": "挪威", "away": "挪威", "injury": "【挪威#36】4-3-3;近5场3胜0平2负(进12失10);莫勒尔沃尔夫⚠️对巴西伤退存疑(左后卫);佩德森✅病愈复出(右后卫);哈兰德✅7球金靴并列(场场进球!18射12正);厄德高✅3助创造力核心;博布🅜+舍尔德鲁普🅜(对巴西双助)替补奇兵;挪威首进8强士气巅峰;但场场失球防守漏洞 | 【英格兰#4】4-2-3-1;近5场4胜1平0负(进11失7);宽萨❌红牌停赛(对墨西哥);里斯詹姆斯✅复出填补防线;斯彭斯右后卫奥莱利左后卫;贝林厄姆✅对墨西哥双响(阿兹特克自1986马拉多纳后首人);凯恩✅5球;赖斯✅;伯恩🅓196cm秘密武器(曾7次零封哈兰德!) | 🌍迈阿密硬石体育场(65K) | 🔥哈兰德(7球)vs贝林厄姆(4球):金球级对决 | H2H:首次世界杯交手 | 上轮2:1胜巴西 | 上轮3:2胜墨西哥", "score": "3:2/2:1", "htft": "胜-胜/平-胜", "totalGoals": "5球/4球", "source": "ai", "code": "周日091"}, {"id": 99, "spf": "2.10/3.40/2.79", "tip": "胜", "level": "🔵中等", "home": "美国", "away": "比利时", "injury": "【西班牙#3】4-3-3;近5场4胜1平0负(进6失0);5场0失球防守历史级!;亚马尔✅腿筋管理可打满(对葡萄牙关键表现);尼科威廉姆斯✅内收肌恢复可出场(对葡萄牙未上);皮诺❌肩伤确认缺阵;罗德里🅜金球级核心;梅里诺🅜对葡萄牙91分绝杀英雄;费兰托雷斯🅕;奥亚萨瓦尔🅕 | 【比利时#9】4-2-3-1;近5场2胜2平1负(进9失3);德布劳内⚠️34岁大腿伤后状态下滑(对埃及平淡被换);多库✅复出(孩子出生后归队);德凯特拉雷✅对USA双响;卢卡库✅超级替补(对USA进球);库尔图瓦🅖;黄金一代最后一届;体能不足(对塞内加尔加时+对USA消耗大) | 🌍洛杉矶SoFi体育场(70K) | 🔥西班牙钢铁防线vs比利时黄金一代谢幕 | H2H:西班牙8胜3平4负(最近2016友谊赛西班牙2-0) | 上轮1:0胜葡萄牙 | 上轮4:1胜美国", "score": "3:2/2:1", "htft": "胜-胜/平-胜", "totalGoals": "5球/4球", "source": "ai", "code": "周一094"}, {"id": 100, "spf": "待定", "tip": "平", "level": "🔵中等", "home": "R16-95胜者", "away": "R16-96胜者", "injury": "【R16-95胜者#50】4-4-2;🅕队长;🅜组织核心;🅓防守核心;首战 | 【R16-96胜者#50】5-4-1;🅕✅核心可出战;🅜✅中场;🅓✅防线;首战 | 🌍堪萨斯城·箭头体育场 | 🔥出线关键战 | H2H:待确认 | 首战 | 首战", "score": "1:1/0:0", "htft": "平平/平-平", "totalGoals": "2球/1球", "source": "template"}, {"id": 101, "spf": "待定", "tip": "平", "level": "🟢铁胆", "note": "半决赛", "home": "挪威", "away": "英格兰", "injury": "【挪威#36】4-4-2;🅕队长;🅜组织核心;🅓防守核心;近3场2胜0平1负(进8失7) | 【英格兰#4】4-2-3-1;🅕✅核心可出战;🅜✅中场;🅓✅防线;近3场2胜1平0负(进6失2) | 🌍达拉斯·AT&T体育场 | 🔥出线关键战 | H2H:待确认 | 上轮1:4负法国 | 上轮0:2胜巴拿马", "score": "3:3/1:1", "htft": "平平/平-平", "totalGoals": "6球/5球", "source": "template"}, {"id": 102, "spf": "待定", "tip": "平", "level": "🟠大概率", "home": "西班牙", "away": "比利时", "injury": "【西班牙#3】4-3-3;🅕队长;🅜组织核心;🅓防守核心;近3场2胜1平0负(进5失0) | 【比利时#8】4-2-3-1;🅕✅核心可出战;🅜✅中场;🅓✅防线;近3场1胜2平0负(进6失2) | 🌍亚特兰大·梅赛德斯-奔驰体育场 | 🔥出线关键战 | H2H:待确认 | 上轮0:1胜乌拉圭 | 上轮1:5胜新西兰", "score": "2:2/1:1", "htft": "平平/平-平", "totalGoals": "4球/3球", "source": "template"}, {"id": 103, "spf": "待定", "tip": "平", "level": "🔵中等", "note": "季军赛", "home": "SF-101负者", "away": "SF-102负者", "injury": "【SF-101负者#50】4-4-2;🅕队长;🅜组织核心;🅓防守核心;首战 | 【SF-102负者#50】5-4-1;🅕✅核心可出战;🅜✅中场;🅓✅防线;首战 | 🌍迈阿密·硬石体育场 | 🔥出线关键战 | H2H:待确认 | 首战 | 首战", "score": "1:1/0:0", "htft": "平平/平-平", "totalGoals": "2球/1球", "source": "template"}, {"id": 104, "spf": "待定", "tip": "平", "level": "🔵中等", "note": "决赛", "home": "SF-101胜者", "away": "SF-102胜者", "injury": "【SF-101胜者#50】4-4-2;🅕队长;🅜组织核心;🅓防守核心;首战 | 【SF-102胜者#50】5-4-1;🅕✅核心可出战;🅜✅中场;🅓✅防线;首战 | 🌍纽约·大都会人寿体育场 | 🔥出线关键战 | H2H:待确认 | 首战 | 首战", "score": "1:1/0:0", "htft": "平平/平-平", "totalGoals": "2球/1球", "source": "template"}], "dimension_coverage": {"D1_伤病标注": "100%", "D2_阵型": "100%", "D3_矛盾": "100%", "D4_外界": "100%", "D5_近期状态": "100%", "D6_H2H": "100%", "D7_排名": "100%", "D8_位置": "100%", "D10_双向": "100%", "D11_上轮": "100%"}, "max_group_id": 72}